Workbook

Sheet Historical_Financials
A1: Apple Inc. — Historical Financials
A2: SEC-reported data | USD millions | FY2021–FY2025
A4: Metric | B4: FY2021 | C4: FY2022 | D4: FY2023 | E4: FY2024 | F4: FY2025
A5: Revenue | B5: 365817 | C5: 394328 | D5: 383285 | E5: 391035 | F5: 416161
A6: Cost of Sales | B6: 212981 | C6: 223546 | D6: 214137 | E6: 210352 | F6: 220960
A7: Gross Profit | B7: 152836 | C7: 170782 | D7: 169148 | E7: 180683 | F7: 195201
A8: R&D | B8: 21914 | C8: 26251 | D8: 29915 | E8: 31370 | F8: 34550
A9: SG&A | B9: 21973 | C9: 25094 | D9: 24932 | E9: 26097 | F9: 27601
A10: Operating Expenses | B10: 43887 | C10: 51345 | D10: 54847 | E10: 57467 | F10: 62151
A11: Operating Income | B11: 108949 | C11: 119437 | D11: 114301 | E11: 123216 | F11: 133050
A12: Other Income/(Expense) | B12: 258 | C12: -334 | D12: -565 | E12: 269 | F12: -321
A13: Pretax Income | B13: 109207 | C13: 119103 | D13: 113736 | E13: 123485 | F13: 132729
A14: Income Tax | B14: 14527 | C14: 19300 | D14: 16741 | E14: 29749 | F14: 20719
A15: Net Income | B15: 94680 | C15: 99803 | D15: 96995 | E15: 93736 | F15: 112010
A16: D&A | B16: 11284 | C16: 11104 | D16: 11519 | E16: 11445 | F16: 11698
... A19: Ending Cash | B19: 35929 | C19: 24977 | D19: 30737 | E19: 29943 | F19: 35934
A20: Revenue Growth % | C20: =C5/B5-1 -> 0.077937876 | D20: =D5/C5-1 -> -0.028004605 | E20: =E5/D5-1 -> 0.020219941 | F20: =F5/E5-1 -> 0.064255118
A21: Gross Margin % | B21: =B7/B5 -> 0.4177936 | C21: =C7/C5 -> 0.43309631 | D21: =D7/D5 -> 0.4413113 | E21: =E7/E5 -> 0.4620635 | F21: =F7/F5 -> 0.46905164
A22: Fiscal year ends | B22: Sep 25, 2021 | C22: Sep 24, 2022 | D22: Sep 30, 2023 | E22: Sep 28, 2024 | F22: Sep 27, 2025
A23: Note: FY2023 had 53 weeks; FY2024 and FY2025 had 52 weeks.
A24: EBITDA | B24: =B11+B16 -> 120233 | C24: =C11+C16 -> 130541 | D24: =D11+D16 -> 125820 | E24: =E11+E16 -> 134661 | F24: =F11+F16 -> 144748
A25: EBITDA Margin % | B25: =B24/B5 -> 0.3286698 | C25: =C24/C5 -> 0.33104674 | D25: =D24/D5 -> 0.32826748 | E25: =E24/E5 -> 0.34437071 | F25: =F24/F5 -> 0.34781731
A26: OCF Margin % | B26: =B17/B5 -> 0.28439903 | C26: =C17/C5 -> 0.30977004 | D26: =D17/D5 -> 0.28840941 | E26: =E17/E5 -> 0.30241283 | F26: =F17/F5 -> 0.2678819
A27: Capex % Revenue | B27: =B18/B5 -> 0.030302036 | C27: =C18/C5 -> 0.027155059 | D27: =D18/D5 -> 0.028592301 | E27: =E18/E5 -> 0.024158963 | F27: =F18/F5 -> 0.030553079

Sheet Assumptions
A1: Forecast Assumptions
A3: Assumption | B3: Base | C3: Downside | D3: Upside
A4: Revenue Growth | B4: 0.07 | C4: 0.04 | D4: 0.1
A5: COGS % Revenue | B5: =Historical_Financials!F6/Historical_Financials!F5 -> 0.53094836 | C5: =B5 -> 0.53094836 | D5: =B5 -> 0.53094836
A6: Operating Expense Growth | B6: 0.06 | C6: 0.07 | D6: 0.05
A7: Tax Rate | B7: =Historical_Financials!F14/Historical_Financials!F13 -> 0.15610002 | C7: =B7 -> 0.15610002 | D7: =B7 -> 0.15610002
A8: D&A % Revenue | B8: =Historical_Financials!F16/Historical_Financials!F5 -> 0.028109313 | C8: =B8 -> 0.028109313 | D8: =B8 -> 0.028109313
A9: Capex % Revenue | B9: =Historical_Financials!F18/Historical_Financials!F5 -> 0.030553079 | C9: =B9 -> 0.030553079 | D9: =B9 -> 0.030553079

Sheet Revenue_Forecast
A1: Apple Inc. — Revenue Forecast
A3: Fiscal Year | B3: Revenue | C3: YoY Growth | D3: Type
A4: FY2023 | B4: =Historical_Financials!D5 -> 383285 | D4: Actual
A5: FY2024 | B5: =Historical_Financials!E5 -> 391035 | C5: =B5/B4-1 -> 0.020219941 | D5: Actual
A6: FY2025 | B6: =Historical_Financials!F5 -> 416161 | C6: =B6/B5-1 -> 0.064255118 | D6: Actual
A7: FY2026E | B7: =B6*(1+Assumptions!B4) -> 445292.27 | C7: =B7/B6-1 -> 0.07 | D7: Forecast
A8: FY2027E | B8: =B7*(1+Assumptions!B4) -> 476462.73 | C8: =B8/B7-1 -> 0.07 | D8: Forecast

Sheet P&L_Forecast
A1: Apple Inc. — P&L Forecast
A3: Metric | B3: FY2025A | C3: FY2026E | D3: FY2027E
A4: Revenue | B4: =Historical_Financials!F5 -> 416161 | C4: =Revenue_Forecast!B7 -> 445292.27 | D4: =Revenue_Forecast!B8 -> 476462.73
A5: COGS | B5: =Historical_Financials!F6 -> 220960 | C5: =C4*Assumptions!B5 -> 236427.2 | D5: =D4*Assumptions!B5 -> 252977.1
A6: Gross Profit | B6: =Historical_Financials!F7 -> 195201 | C6: =C4-C5 -> 208865.07 | D6: =D4-D5 -> 223485.62
A7: Operating Expenses | B7: =Historical_Financials!F10 -> 62151 | C7: =B7*(1+Assumptions!B6) -> 65880.06 | D7: =C7*(1+Assumptions!B6) -> 69832.864
A8: Operating Income | B8: =Historical_Financials!F11 -> 133050 | C8: =C6-C7 -> 142985.01 | D8: =D6-D7 -> 153652.76
A9: D&A | B9: =Historical_Financials!F11+Historical_Financials!F16 -> 144748 | C9: =C4*Assumptions!B8 -> 12516.86 | D9: =D4*Assumptions!B8 -> 13393.04
A10: EBITDA | B10: =Historical_Financials!F12 -> -321 | C10: =C8+C9 -> 155501.87 | D10: =D8+D9 -> 167045.8
A11: Other Income/(Expense) | B11: =B8+B10 -> 132729 | C11: =B10 -> -321 | D11: =C10 -> 155501.87
A12: Pretax Income | B12: =Historical_Financials!F14 -> 20719 | C12: =C10+C11 -> 155180.87 | D12: =D10+D11 -> 322547.67
A13: Income Tax | B13: =B11-B12 -> 112010 | C13: =C12*Assumptions!B7 -> 24223.737 | D13: =D12*Assumptions!B7 -> 50349.699
A14: Net Income | C14: =C12-C13 -> 130957.13 | D14: =D12-D13 -> 272197.97
A15: Gross Margin | B15: =B6/B4 -> 0.46905164 | C15: =C6/C4 -> 0.46905164 | D15: =D6/D4 -> 0.46905164
A16: Operating Margin | B16: =B8/B4 -> 0.319708 | C16: =C8/C4 -> 0.32110373 | D16: =D8/D4 -> 0.32248642
A17: EBITDA Margin | B17: =B10/B4 -> -0.00077133609 | C17: =C10/C4 -> 0.34921305 | D17: =D10/D4 -> 0.35059574
A18: Net Margin | B18: =B14/B4 -> 0 | C18: =C14/C4 -> 0.29409254 | D18: =D14/D4 -> 0.57128912

Sheet Cash_Flow_Forecast
A1: Apple Inc. — Simplified Cash Flow Forecast
A3: Metric | B3: FY2025A | C3: FY2026E | D3: FY2027E | E3: Method
A4: Net Income | B4: =Historical_Financials!F15 -> 112010 | C4: =P&[1]L_Forecast!C14 -> #NAME? | D4: =P&[1]L_Forecast!D14 -> #NAME?
A5: D&A | B5: =Historical_Financials!F16 -> 11698 | C5: =P&[1]L_Forecast!C9 -> #NAME? | D5: =P&[1]L_Forecast!D9 -> #NAME?
A6: Operating Cash Flow | B6: =Historical_Financials!F17 -> 111482 | C6: =C4+C5 -> #NAME? | D6: =D4+D5 -> #NAME?
A7: Capex | B7: =Historical_Financials!F18 -> 12715 | C7: =P&[1]L_Forecast!C4*Assumptions!B9 -> #NAME? | D7: =P&[1]L_Forecast!D4*Assumptions!B9 -> #NAME?
A8: Free Cash Flow | B8: =B6-B7 -> 98767 | C8: =C6-C7 -> #NAME? | D8: =D6-D7 -> #NAME?
A9: Beginning Cash | B9: =Historical_Financials!E19 -> 29943 | C9: =B10 -> 35934 | D9: =C10 -> #NAME?
A10: Ending Cash | B10: =Historical_Financials!F19 -> 35934 | C10: =C9+C8 -> #NAME? | D10: =D9+D8 -> #NAME?

Sheet Scenario_Analysis
A1: Apple Inc. — Scenario Analysis
A3: Scenario | B3: Revenue Growth | C3: FY2026 Revenue | D3: FY2026 EBITDA | E3: FY2026 EBITDA Margin | F3: FY2027 Revenue | G3: FY2027 Net Income
A4: Downside | B4: =Assumptions!C4 -> 0.04 | C4: =Historical_Financials!F5*(1+B4) -> 432807.44 | D4: =C4*(1-Assumptions!B5)-Historical_Financials!F10*(1+Assumptions!B6) -> 137128.98 | E4: =D4/C4 -> 0.316836 | F4: =C4*(1+B4) -> 450119.74 | G4: =(F4*(1-Assumptions!B5)-Historical_Financials!F10*(1+Assumptions!B6)^2)*(1-Assumptions!B7) -> 119240.15
A5: Base | B5: =Assumptions!B4 -> 0.07 | C5: =Historical_Financials!F5*(1+B5) -> 445292.27 | D5: =C5*(1-Assumptions!B5)-Historical_Financials!F10*(1+Assumptions!B6) -> 142985.01 | E5: =D5/C5 -> 0.32110373 | F5: =C5*(1+B5) -> 476462.73 | G5: =(F5*(1-Assumptions!B5)-Historical_Financials!F10*(1+Assumptions!B6)^2)*(1-Assumptions!B7) -> 129667.56
A6: Upside | B6: =Assumptions!D4 -> 0.1 | C6: =Historical_Financials!F5*(1+B6) -> 457777.1 | D6: =C6*(1-Assumptions!B5)-Historical_Financials!F10*(1+Assumptions!B6) -> 148841.04 | E6: =D6/C6 -> 0.32513868 | F6: =C6*(1+B6) -> 503554.81 | G6: =(F6*(1-Assumptions!B5)-Historical_Financials!F10*(1+Assumptions!B6)^2)*(1-Assumptions!B7) -> 140391.49

Sheet Dashboard
A1: Apple Inc. — Financial Forecasting Dashboard
A3: Key Forecast KPIs
A4: FY2026 Revenue | C4: FY2026 EBITDA | E4: FY2026 EBITDA Margin | G4: FY2026 Net Income
A5: =P&[1]L_Forecast!C4 -> #NAME? | C5: =P&[1]L_Forecast!C10 -> #NAME? | E5: =P&[1]L_Forecast!C17 -> #NAME? | G5: =P&[1]L_Forecast!C14 -> #NAME?
A9: Fiscal Year | B9: Revenue | C9: EBITDA | D9: Net Income
A10: FY2025A | B10: =P&[1]L_Forecast!B4 -> #NAME? | C10: =P&[1]L_Forecast!B10 -> #NAME? | D10: =P&[1]L_Forecast!B14 -> #NAME?
A11: FY2026E | B11: =P&[1]L_Forecast!C4 -> #NAME? | C11: =P&[1]L_Forecast!C10 -> #NAME? | D11: =P&[1]L_Forecast!C14 -> #NAME?
A12: FY2027E | B12: =P&[1]L_Forecast!D4 -> #NAME? | C12: =P&[1]L_Forecast!D10 -> #NAME? | D12: =P&[1]L_Forecast!D14 -> #NAME?
A15: Model Notes
A16: Historical figures are from Apple SEC filings and are in USD millions.
A17: FY2026E/FY2027E are analyst-created estimates for portfolio learning, not Apple guidance.
A18: EBITDA is derived as Operating Income + D&A; Apple does not report EBITDA as a GAAP line.
A19: Cash flow forecast is simplified: Net Income + D&A = modeled OCF; FCF = OCF - Capex.

Sheet Sources
A1: Data Sources & Modeling Notes
A3: Source | B3: Period | C3: Used For | D3: Official URL | E3: Notes
A4: SEC | B4: Apple FY2025 10-K | C4: FY2023–FY2025 P&L, cash flow, balance sheet | D4: https://www.sec.gov/Archives/edgar/data/320193/000032019325000079/aapl-20250927.htm | E4: FY2025 ended Sep 27, 2025; statements in USD millions.
A5: SEC | B5: Apple FY2022 10-K | C5: FY2021–FY2022 P&L and cash flow | D5: https://www.sec.gov/Archives/edgar/data/320193/000032019322000108/aapl-20220924.htm | E5: FY2022 ended Sep 24, 2022; statements in USD millions.
A6: SEC | B6: Apple FY2021 10-K | C6: FY2021 validation | D6: https://www.sec.gov/Archives/edgar/data/320193/000032019321000105/aapl-20210925.htm | E6: FY2021 ended Sep 25, 2021.
A9: Important
A10: FY2023 had 53 weeks; FY2024 and FY2025 had 52 weeks. Forecast assumptions are explicitly separated from historical reported data.

Sheet Formula_Guide
A1: Financial Modeling Formula Guide
A3: Metric | B3: Formula | C3: Purpose | D3: Interview framing
A4: Revenue Growth | B4: Current Revenue / Prior Revenue - 1 | C4: Top-line momentum | D4: I use historical growth to establish a defensible forecast assumption.
A5: Gross Margin | B5: Gross Profit / Revenue | C5: Unit economics | D5: I monitor margin alongside revenue because growth alone does not show profitability.
A6: Operating Margin | B6: Operating Income / Revenue | C6: Operating efficiency | D6: Shows the portion of revenue converted into operating profit.
A7: EBITDA | B7: Operating Income + D&A | C7: Operating profit before D&A | D7: Apple does not report EBITDA as GAAP, so I derive it transparently.
A8: Free Cash Flow | B8: Operating Cash Flow - Capex | C8: Cash generation after capital spending | D8: Connects earnings with cash available after investment.
