Workbook

Sheet README
A1: Project 3 — Canara Bank vs Axis Bank Financial Statement Analysis
A3: Objective | B3: Analyze five years of bank financial performance using profitability, growth, balance-sheet scale and asset-quality indicators.
A4: Period | B4: FY2020-21 to FY2024-25 (FY2021–FY2025).
A5: Units | B5: ₹ crore for monetary figures; percentages for ratios.
A6: Banks | B6: Canara Bank and Axis Bank.
A7: Core question | B7: How did growth, profitability and asset quality change over five years, and what are the major drivers?
A8: Workflow | B8: Source → Extract → Standardize → Calculate → Compare → Interpret → Present.
A9: Important | B9: Bank analysis is different from industrial-company analysis. NII, NIM, NPA, ROA and ROE are key banking metrics.
A10: Cost-to-income | B10: Canara Bank has a reported five-year-compatible series in the project dataset. Axis Bank's annual-report KPI disclosure uses cost-to-assets; therefore Axis cost-to-income is intentionally not forced into the comparable dataset.
A13: Project structure
A14: • Historical_Data — source-level five-year dataset
A15: • Calculations — growth, CAGR, changes and comparison formulas
A16: • Ratio_Analysis — banking ratios and interpretation fields
A17: • Dashboard — management-style charts and KPIs
A18: • Source_Log — source, page/section and extraction notes
A19: • Insights — final analyst observations
A20: • Interview_Story — explain the project in an interview
A21: • Reverse_Engineering — what each section is doing and why

Sheet Historical_Data
A1: Historical Bank Data — FY2021 to FY2025
A3: Bank | B3: Metric | C3: FY2021 | D3: FY2022 | E3: FY2023 | F3: FY2024 | G3: FY2025 | H3: Unit
A4: Canara Bank | B4: Net Interest Income | C4: 24103 | D4: 26384 | E4: 31435 | F4: 36566 | G4: 37072 | H4: ₹ crore
A5: Canara Bank | B5: Net Profit | C5: 2558 | D5: 5678 | E5: 10604 | F5: 14554 | G5: 17027 | H5: ₹ crore
A6: Canara Bank | B6: Total Assets | C6: 1153675 | D6: 1226980 | E6: 1345732 | F6: 1491541 | G6: 1682850 | H6: ₹ crore
A7: Canara Bank | B7: Total Deposits | C7: 1010875 | D7: 1086409 | E7: 1179219 | F7: 1312366 | G7: 1456883 | H7: ₹ crore
A8: Canara Bank | B8: Advances | C8: 675155 | D8: 741147 | E8: 862782 | F8: 960602 | G8: 1073332 | H8: ₹ crore
A9: Canara Bank | B9: Gross NPA | C9: 8.93 | D9: 7.51 | E9: 5.35 | F9: 4.23 | G9: 2.94 | H9: %
A10: Canara Bank | B10: Net NPA | C10: 3.82 | D10: 2.65 | E10: 1.73 | F10: 1.27 | G10: 0.7 | H10: %
A11: Canara Bank | B11: ROA | C11: 0.23 | D11: 0.48 | E11: 0.81 | F11: 1.01 | G11: 1.09 | H11: %
A12: Canara Bank | B12: ROE | C12: 6.71 | D12: 12.82 | E12: 19.49 | F12: 22.06 | G12: 21.28 | H12: %
A13: Canara Bank | B13: Cost-to-Income | C13: 49.55 | D13: 46.16 | E13: 44.79 | F13: 47.03 | G13: 47.27 | H13: %
A14: Canara Bank | B14: NIM | C14: 2.75 | D14: 2.95 | E14: 3.02 | F14: 3.05 | G14: 2.8 | H14: %
A15: Axis Bank | B15: Net Interest Income | C15: 29239 | D15: 33132 | E15: 42946 | F15: 49894 | G15: 54348 | H15: ₹ crore
... A23: Axis Bank | B23: ROE | C23: 7.55 | D23: 12.91 | E23: 18.38 | F23: 18.86 | G23: 16.52 | H23: %
A24: Axis Bank | B24: Cost-to-Income | H24: % — not forced
A25: Axis Bank | B25: NIM | C25: 3.56 | D25: 3.54 | E25: 4.22 | F25: 4.07 | G25: 3.98 | H25: %

Sheet Calculations
A1: Growth & Trend Calculations
A3: Bank | B3: Metric | C3: FY2021 | D3: FY2022 | E3: FY2023 | F3: FY2024 | G3: FY2025 | H3: 5Y Change | I3: 5Y CAGR | J3: Interpretation
A4: Canara Bank | B4: Net Interest Income | C4: =Historical_Data!C4 -> 24103 | D4: =Historical_Data!D4 -> 26384 | E4: =Historical_Data!E4 -> 31435 | F4: =Historical_Data!F4 -> 36566 | G4: =Historical_Data!G4 -> 37072 | H4: =G4/C4-1 -> 0.5380658 | I4: =(G4/C4)^(1/4)-1 -> 0.1136372 | J4: 5-year growth trend
A5: Canara Bank | B5: Net Profit | C5: =Historical_Data!C5 -> 2558 | D5: =Historical_Data!D5 -> 5678 | E5: =Historical_Data!E5 -> 10604 | F5: =Historical_Data!F5 -> 14554 | G5: =Historical_Data!G5 -> 17027 | H5: =G5/C5-1 -> 5.6563722 | I5: =(G5/C5)^(1/4)-1 -> 0.60623616 | J5: 5-year growth trend
A6: Canara Bank | B6: Total Deposits | C6: =Historical_Data!C7 -> 1010875 | D6: =Historical_Data!D7 -> 1086409 | E6: =Historical_Data!E7 -> 1179219 | F6: =Historical_Data!F7 -> 1312366 | G6: =Historical_Data!G7 -> 1456883 | H6: =G6/C6-1 -> 0.44120984 | I6: =(G6/C6)^(1/4)-1 -> 0.095675132 | J6: 5-year growth trend
A7: Canara Bank | B7: Advances | C7: =Historical_Data!C8 -> 675155 | D7: =Historical_Data!D8 -> 741147 | E7: =Historical_Data!E8 -> 862782 | F7: =Historical_Data!F8 -> 960602 | G7: =Historical_Data!G8 -> 1073332 | H7: =G7/C7-1 -> 0.58975643 | I7: =(G7/C7)^(1/4)-1 -> 0.12287819 | J7: 5-year growth trend
A8: Canara Bank | B8: Total Assets | C8: =Historical_Data!C6 -> 1153675 | D8: =Historical_Data!D6 -> 1226980 | E8: =Historical_Data!E6 -> 1345732 | F8: =Historical_Data!F6 -> 1491541 | G8: =Historical_Data!G6 -> 1682850 | H8: =G8/C8-1 -> 0.45868637 | I8: =(G8/C8)^(1/4)-1 -> 0.098981752 | J8: 5-year growth trend
A9: Axis Bank | B9: Net Interest Income | C9: =Historical_Data!C15 -> 29239 | D9: =Historical_Data!D15 -> 33132 | E9: =Historical_Data!E15 -> 42946 | F9: =Historical_Data!F15 -> 49894 | G9: =Historical_Data!G15 -> 54348 | H9: =G9/C9-1 -> 0.8587503 | I9: =(G9/C9)^(1/4)-1 -> 0.16763005 | J9: 5-year growth trend
A10: Axis Bank | B10: Net Profit | C10: =Historical_Data!C16 -> 6589 | D10: =Historical_Data!D16 -> 13025 | E10: =Historical_Data!E16 -> 21933 | F10: =Historical_Data!F16 -> 24861 | G10: =Historical_Data!G16 -> 26373 | H10: =G10/C10-1 -> 3.0025801 | I10: =(G10/C10)^(1/4)-1 -> 0.41444155 | J10: 5-year growth trend
A11: Axis Bank | B11: Total Deposits | C11: =Historical_Data!C18 -> 697985 | D11: =Historical_Data!D18 -> 821721 | E11: =Historical_Data!E18 -> 946945 | F11: =Historical_Data!F18 -> 1068641 | G11: =Historical_Data!G18 -> 1172952 | H11: =G11/C11-1 -> 0.6804831 | I11: =(G11/C11)^(1/4)-1 -> 0.13856686 | J11: 5-year growth trend
A12: Axis Bank | B12: Advances | C12: =Historical_Data!C19 -> 614399 | D12: =Historical_Data!D19 -> 707947 | E12: =Historical_Data!E19 -> 845303 | F12: =Historical_Data!F19 -> 965068 | G12: =Historical_Data!G19 -> 1040811 | H12: =G12/C12-1 -> 0.69403108 | I12: =(G12/C12)^(1/4)-1 -> 0.14085472 | J12: 5-year growth trend
A13: Axis Bank | B13: Total Assets | C13: =Historical_Data!C17 -> 986798 | D13: =Historical_Data!D17 -> 1175429 | E13: =Historical_Data!E17 -> 1317326 | F13: =Historical_Data!F17 -> 1477209 | G13: =Historical_Data!G17 -> 1609930 | H13: =G13/C13-1 -> 0.63146865 | I13: =(G13/C13)^(1/4)-1 -> 0.13017236 | J13: 5-year growth trend
A15: Bank | B15: Metric | C15: FY2021 | D15: FY2025 | E15: Absolute Change
A16: Canara Bank | B16: Gross NPA | C16: =Historical_Data!C9 -> 8.93 | D16: =Historical_Data!G9 -> 2.94 | E16: =D16-C16 -> -5.99
A17: Canara Bank | B17: Net NPA | C17: =Historical_Data!C10 -> 3.82 | D17: =Historical_Data!G10 -> 0.7 | E17: =D17-C17 -> -3.12
A18: Canara Bank | B18: ROA | C18: =Historical_Data!C11 -> 0.23 | D18: =Historical_Data!G11 -> 1.09 | E18: =D18-C18 -> 0.86
A19: Canara Bank | B19: ROE | C19: =Historical_Data!C12 -> 6.71 | D19: =Historical_Data!G12 -> 21.28 | E19: =D19-C19 -> 14.57
A20: Axis Bank | B20: Gross NPA | C20: =Historical_Data!C20 -> 3.7 | D20: =Historical_Data!G20 -> 1.28 | E20: =D20-C20 -> -2.42
A21: Axis Bank | B21: Net NPA | C21: =Historical_Data!C21 -> 1.05 | D21: =Historical_Data!G21 -> 0.33 | E21: =D21-C21 -> -0.72
A22: Axis Bank | B22: ROA | C22: =Historical_Data!C22 -> 0.7 | D22: =Historical_Data!G22 -> 1.74 | E22: =D22-C22 -> 1.04
A23: Axis Bank | B23: ROE | C23: =Historical_Data!C23 -> 7.55 | D23: =Historical_Data!G23 -> 16.52 | E23: =D23-C23 -> 8.97

Sheet Ratio_Analysis
A1: Banking Ratio Analysis
A3: Bank | B3: Ratio | C3: FY2021 | D3: FY2022 | E3: FY2023 | F3: FY2024 | G3: FY2025 | H3: What it tells an analyst
A4: Canara Bank | B4: Gross NPA | C4: =Historical_Data!C9 -> 8.93 | D4: =Historical_Data!D9 -> 7.51 | E4: =Historical_Data!E9 -> 5.35 | F4: =Historical_Data!F9 -> 4.23 | G4: =Historical_Data!G9 -> 2.94 | H4: Asset quality; higher NPA indicates greater stressed assets
A5: Canara Bank | B5: Net NPA | C5: =Historical_Data!C10 -> 3.82 | D5: =Historical_Data!D10 -> 2.65 | E5: =Historical_Data!E10 -> 1.73 | F5: =Historical_Data!F10 -> 1.27 | G5: =Historical_Data!G10 -> 0.7 | H5: Net stressed assets after provisions
A6: Canara Bank | B6: NIM | C6: =Historical_Data!C14 -> 2.75 | D6: =Historical_Data!D14 -> 2.95 | E6: =Historical_Data!E14 -> 3.02 | F6: =Historical_Data!F14 -> 3.05 | G6: =Historical_Data!G14 -> 2.8 | H6: Interest spread generated from banking assets
A7: Canara Bank | B7: ROA | C7: =Historical_Data!C11 -> 0.23 | D7: =Historical_Data!D11 -> 0.48 | E7: =Historical_Data!E11 -> 0.81 | F7: =Historical_Data!F11 -> 1.01 | G7: =Historical_Data!G11 -> 1.09 | H7: Profitability relative to assets
A8: Canara Bank | B8: ROE | C8: =Historical_Data!C12 -> 6.71 | D8: =Historical_Data!D12 -> 12.82 | E8: =Historical_Data!E12 -> 19.49 | F8: =Historical_Data!F12 -> 22.06 | G8: =Historical_Data!G12 -> 21.28 | H8: Profitability relative to shareholders' equity
A9: Axis Bank | B9: Gross NPA | C9: =Historical_Data!C20 -> 3.7 | D9: =Historical_Data!D20 -> 2.82 | E9: =Historical_Data!E20 -> 2.02 | F9: =Historical_Data!F20 -> 1.43 | G9: =Historical_Data!G20 -> 1.28 | H9: Asset quality; higher NPA indicates greater stressed assets
A10: Axis Bank | B10: Net NPA | C10: =Historical_Data!C21 -> 1.05 | D10: =Historical_Data!D21 -> 0.73 | E10: =Historical_Data!E21 -> 0.39 | F10: =Historical_Data!F21 -> 0.31 | G10: =Historical_Data!G21 -> 0.33 | H10: Net stressed assets after provisions
A11: Axis Bank | B11: NIM | C11: =Historical_Data!C25 -> 3.56 | D11: =Historical_Data!D25 -> 3.54 | E11: =Historical_Data!E25 -> 4.22 | F11: =Historical_Data!F25 -> 4.07 | G11: =Historical_Data!G25 -> 3.98 | H11: Interest spread generated from banking assets
A12: Axis Bank | B12: ROA | C12: =Historical_Data!C22 -> 0.7 | D12: =Historical_Data!D22 -> 1.21 | E12: =Historical_Data!E22 -> 1.82 | F12: =Historical_Data!F22 -> 1.83 | G12: =Historical_Data!G22 -> 1.74 | H12: Profitability relative to assets
A13: Axis Bank | B13: ROE | C13: =Historical_Data!C23 -> 7.55 | D13: =Historical_Data!D23 -> 12.91 | E13: =Historical_Data!E23 -> 18.38 | F13: =Historical_Data!F23 -> 18.86 | G13: =Historical_Data!G23 -> 16.52 | H13: Profitability relative to shareholders' equity

Sheet Dashboard
A1: Canara Bank vs Axis Bank — Management Dashboard
A3: FY2025 Snapshot
A4: Canara NII | D4: Axis NII | G4: Canara Profit | J4: Axis Profit
A5: =Historical_Data!G4 -> 37072 | D5: =Historical_Data!G15 -> 54348 | G5: =Historical_Data!G5 -> 17027 | J5: =Historical_Data!G16 -> 26373
A7: Canara ROA | D7: Axis ROA | G7: Canara Gross NPA | J7: Axis Gross NPA
A8: =Historical_Data!G11 -> 1.09 | D8: =Historical_Data!G20 -> 1.28 | G8: =Historical_Data!G9 -> 2.94 | J8: =Historical_Data!G21 -> 0.33
A11: FY | B11: FY2021 | C11: FY2022 | D11: FY2023 | E11: FY2024 | F11: FY2025
A12: Canara Bank | B12: =Historical_Data!C5 -> 2558 | C12: =Historical_Data!D5 -> 5678 | D12: =Historical_Data!E5 -> 10604 | E12: =Historical_Data!F5 -> 14554 | F12: =Historical_Data!G5 -> 17027
A13: Axis Bank | B13: =Historical_Data!C16 -> 6589 | C13: =Historical_Data!D16 -> 13025 | D13: =Historical_Data!E16 -> 21933 | E13: =Historical_Data!F16 -> 24861 | F13: =Historical_Data!G16 -> 26373
A26: FY | B26: FY2021 | C26: FY2022 | D26: FY2023 | E26: FY2024 | F26: FY2025
A27: Canara Bank | B27: =Historical_Data!C9 -> 8.93 | C27: =Historical_Data!D9 -> 7.51 | D27: =Historical_Data!E9 -> 5.35 | E27: =Historical_Data!F9 -> 4.23 | F27: =Historical_Data!G9 -> 2.94
A28: Axis Bank | B28: =Historical_Data!C21 -> 1.05 | C28: =Historical_Data!D21 -> 0.73 | D28: =Historical_Data!E21 -> 0.39 | E28: =Historical_Data!F21 -> 0.31 | F28: =Historical_Data!G21 -> 0.33

Sheet Source_Log
A1: Source & Extraction Log
A3: Bank | B3: Fiscal Year | C3: Metric Group | D3: Primary Source | E3: Location / Section | F3: Unit | G3: Status | H3: Notes
A4: Canara Bank | B4: FY2024-25 | C4: Key financial ratios | D4: Canara Bank FY2024-25 Annual Report | E4: Key Financial Ratios / Chairman's Statement | F4: ₹ crore / % | G4: Primary | H4: Annual report includes FY2024 and FY2025 ratio disclosures.
A5: Canara Bank | B5: FY2020-21 to FY2024-25 | C5: Five-year financial data | D5: Canara Bank Annual Reports | E5: Five-year summaries / financial highlights | F5: ₹ crore / % | G5: Primary annual-report series | H5: Use the relevant year's annual report to trace each historical point.
A6: Axis Bank | B6: FY2024-25 | C6: ROA/ROE/NPA | D6: Axis Bank FY2024-25 Integrated Annual Report | E6: Business Performance Review / Key Ratios | F6: % | G6: Primary | H6: Five-year ratio series is explicitly disclosed.
A7: Axis Bank | B7: FY2024-25 | C7: NIM | D7: Axis Bank FY2024-25 Statutory Reports | E7: Key Performance Indicators | F7: % | G7: Primary | H7: FY2025 NIM = 3.98%.
A8: Axis Bank | B8: FY2020-21 to FY2024-25 | C8: NII/profit/assets/deposits/advances | D8: Axis Bank annual reports | E8: Financial highlights / financial statements | F8: ₹ crore | G8: Primary annual-report series | H8: Trace historical values to the corresponding annual-report disclosures before publication.
A11: Official links
A12: Axis FY2024-25 Annual Report | B12: https://www.axisbank.com/docs/default-source/annual-reports/for-axis-bank/annual-report-for-the-year-2024-2025.pdf
A13: Axis FY2024-25 Statutory Reports | B13: https://www.axisbank.com/annual-reports/2024-2025/pdf/Statutory%20reports.pdf
A14: Canara FY2024-25 Annual Report | B14: https://canarabank.com/UploadedFiles/Pdf/Annual%20Report%20%E2%80%93%202024-25.pdf

Sheet Insights
A1: Management Insights — Example Analyst Output
A3: Use these as a model for how to write observations. Replace with your own wording after reverse-engineering the calculations.
A5: 1. Growth | B5: Compare five-year NII, deposits and advances growth to understand balance-sheet expansion and core interest-income growth.
A6: 2. Profitability | B6: Track net profit together with ROA and ROE. Profit growth alone can be misleading if the asset/equity base is also expanding.
A7: 3. Asset quality | B7: Gross and net NPA trends indicate changes in stressed assets and credit-quality conditions.
A8: 4. Efficiency | B8: Use cost-to-income only when the numerator and denominator are defined consistently across banks. Do not mix a bank's cost-to-assets ratio with another bank's cost-to-income ratio.
A9: 5. Overall interpretation | B9: The final conclusion should combine growth, profitability, asset quality and efficiency rather than selecting a bank from one metric alone.

Sheet Interview_Story
A1: Interview Story — Canara Bank vs Axis Bank
A3: Project | B3: Five-Year Financial Statement Analysis — Canara Bank vs Axis Bank
A4: Objective | B4: Analyze growth, profitability, asset quality and banking efficiency using five years of reported financial data.
A5: Data | B5: Annual reports and statutory disclosures; monetary values standardized to ₹ crore and ratios to percentages.
A6: Process | B6: I collected historical NII, profit, deposits, advances, assets and banking ratios; standardized the units; calculated growth and five-year changes; then built a dashboard.
A7: Analysis | B7: I compared NII and profit growth, deposit and advance expansion, ROA/ROE trends, and Gross/Net NPA trends.
A8: Key learning | B8: Bank financial analysis requires sector-specific metrics. Traditional industrial-company metrics such as COGS and gross margin are not the main framework for banks.
A9: Business value | B9: The model converts reported financial statements into a concise management view of growth, profitability, asset quality and operating efficiency.

Sheet Reverse_Engineering
A1: Reverse Engineering Guide
A3: Step | B3: Sheet | C3: What to reverse-engineer | D3: Key question
A4: 1 | B4: Historical_Data | C4: Understand what each raw metric means and where it came from. | D4: Source → metric → year → unit
A5: 2 | B5: Calculations | C5: Trace FY2021 and FY2025 values, then inspect the change and CAGR formulas. | D5: Ending / Beginning - 1; CAGR = (Ending/Beginning)^(1/4)-1
A6: 3 | B6: Ratio_Analysis | C6: Understand why NPA, NIM, ROA and ROE are relevant to banks. | D6: Credit quality + spread + profitability
A7: 4 | B7: Dashboard | C7: Identify which raw cells feed each KPI card and chart. | D7: Raw data → dashboard references
A8: 5 | B8: Source_Log | C8: Learn professional data provenance. | D8: Company report → section → metric → unit
A9: 6 | B9: Insights | C9: Translate numerical movements into business questions rather than just describing numbers. | D9: What changed? Why might it matter? What would I investigate next?
A10: 7 | B10: Interview_Story | C10: Practice explaining the workflow without memorizing the wording. | D10: Source → clean → calculate → analyze → communicate
