Workbook

Sheet Raw_Data
A1: Transaction_ID | B1: Date | C1: Month | D1: Department | E1: Expense_Category | F1: Vendor | G1: Budget | H1: Actual | I1: Variance | J1: Variance_%
A2: TXN0001 | B2: 46046 | C2: Jan | D2: IT | E2: Marketing | F2: Google | G2: 187621 | H2: 167800 | I2: =H2-G2 -> -19821 | J2: =IFERROR(I2/G2,0) -> -0.10564382
A3: TXN0002 | B3: 46044 | C3: Jan | D3: Sales | E3: Software | F3: IBM | G3: 56579 | H3: 64800 | I3: =H3-G3 -> 8221 | J3: =IFERROR(I3/G3,0) -> 0.14530126
A4: TXN0003 | B4: 46025 | C4: Jan | D4: HR | E4: Marketing | F4: Oracle | G4: 130604 | H4: 112700 | I4: =H4-G4 -> -17904 | J4: =IFERROR(I4/G4,0) -> -0.13708615
A5: TXN0004 | B5: 46029 | C5: Jan | D5: Sales | E5: Training | F5: Google | G5: 177815 | H5: 153000 | I5: =H5-G5 -> -24815 | J5: =IFERROR(I5/G5,0) -> -0.13955516
A6: TXN0005 | B6: 46048 | C6: Jan | D6: Finance | E6: Travel | F6: Infosys | G6: 137757 | H6: 149600 | I6: =H6-G6 -> 11843 | J6: =IFERROR(I6/G6,0) -> 0.085970223
A7: TXN0006 | B7: 46029 | C7: Jan | D7: IT | E7: Software | F7: Deloitte | G7: 109194 | H7: 105000 | I7: =H7-G7 -> -4194 | J7: =IFERROR(I7/G7,0) -> -0.038408704
A8: TXN0007 | B8: 46050 | C8: Jan | D8: IT | E8: Office | F8: Microsoft | G8: 119595 | H8: 106300 | I8: =H8-G8 -> -13295 | J8: =IFERROR(I8/G8,0) -> -0.11116685
A9: TXN0008 | B9: 46035 | C9: Jan | D9: Finance | E9: Office | F9: IBM | G9: 140435 | H9: 149500 | I9: =H9-G9 -> 9065 | J9: =IFERROR(I9/G9,0) -> 0.064549436
A10: TXN0009 | B10: 46045 | C10: Jan | D10: Finance | E10: Salaries | F10: Google | G10: 114800 | H10: 124100 | I10: =H10-G10 -> 9300 | J10: =IFERROR(I10/G10,0) -> 0.081010453
A11: TXN0010 | B11: 46050 | C11: Jan | D11: HR | E11: Software | F11: Infosys | G11: 95861 | H11: 119300 | I11: =H11-G11 -> 23439 | J11: =IFERROR(I11/G11,0) -> 0.24451028
A12: TXN0011 | B12: 46049 | C12: Jan | D12: IT | E12: Travel | F12: TCS | G12: 92869 | H12: 95800 | I12: =H12-G12 -> 2931 | J12: =IFERROR(I12/G12,0) -> 0.031560585
A13: TXN0012 | B13: 46031 | C13: Jan | D13: Sales | E13: Software | F13: IBM | G13: 113132 | H13: 105600 | I13: =H13-G13 -> -7532 | J13: =IFERROR(I13/G13,0) -> -0.066577096
... A1001: TXN1000 | B1001: 46373 | C1001: Dec | D1001: IT | E1001: Salaries | F1001: Accenture | G1001: 183900 | H1001: 178600 | I1001: =H1001-G1001 -> -5300 | J1001: =IFERROR(I1001/G1001,0) -> -0.028820011

Sheet Analysis
A1: FINANCIAL PERFORMANCE ANALYSIS
A3: Executive KPIs
A5: Total Budget | B5: =SUM(Raw_Data!G2:G1001) -> 113174880
A6: Total Actual | B6: =SUM(Raw_Data!H2:H1001) -> 119473700
A7: Total Variance | B7: =B6-B5 -> 6298820
A8: Overall Variance % | B8: =IFERROR(B7/B5,0) -> 0.055655637
A9: Favorable Transactions | B9: =COUNTIF(Raw_Data!I2:I1001,"<0") -> 348
A10: Unfavorable Transactions | B10: =COUNTIF(Raw_Data!I2:I1001,">0") -> 652
A12: Department Analysis
A13: Item | B13: Budget | C13: Actual | D13: Variance | E13: Variance %
A14: Finance | B14: =SUMIF(Raw_Data!D:D,A14,Raw_Data!G:G) -> 18868433 | C14: =SUMIF(Raw_Data!D:D,A14,Raw_Data!H:H) -> 20183700 | D14: =C14-B14 -> 1315267 | E14: =IFERROR(D14/B14,0) -> 0.069707272
A15: HR | B15: =SUMIF(Raw_Data!D:D,A15,Raw_Data!G:G) -> 20254704 | C15: =SUMIF(Raw_Data!D:D,A15,Raw_Data!H:H) -> 21281700 | D15: =C15-B15 -> 1026996 | E15: =IFERROR(D15/B15,0) -> 0.050704073
A16: IT | B16: =SUMIF(Raw_Data!D:D,A16,Raw_Data!G:G) -> 19424756 | C16: =SUMIF(Raw_Data!D:D,A16,Raw_Data!H:H) -> 20610700 | D16: =C16-B16 -> 1185944 | E16: =IFERROR(D16/B16,0) -> 0.061053225
A17: Marketing | B17: =SUMIF(Raw_Data!D:D,A17,Raw_Data!G:G) -> 18129987 | C17: =SUMIF(Raw_Data!D:D,A17,Raw_Data!H:H) -> 19245100 | D17: =C17-B17 -> 1115113 | E17: =IFERROR(D17/B17,0) -> 0.061506553
A18: Operations | B18: =SUMIF(Raw_Data!D:D,A18,Raw_Data!G:G) -> 17668634 | C18: =SUMIF(Raw_Data!D:D,A18,Raw_Data!H:H) -> 18419500 | D18: =C18-B18 -> 750866 | E18: =IFERROR(D18/B18,0) -> 0.042497117
A19: Sales | B19: =SUMIF(Raw_Data!D:D,A19,Raw_Data!G:G) -> 18828366 | C19: =SUMIF(Raw_Data!D:D,A19,Raw_Data!H:H) -> 19733000 | D19: =C19-B19 -> 904634 | E19: =IFERROR(D19/B19,0) -> 0.048046336
A23: Expense Category Analysis
A24: Item | B24: Budget | C24: Actual | D24: Variance | E24: Variance %
A25: Salaries | B25: =SUMIF(Raw_Data!E:E,A25,Raw_Data!G:G) -> 12978525 | C25: =SUMIF(Raw_Data!E:E,A25,Raw_Data!H:H) -> 13887000 | D25: =C25-B25 -> 908475 | E25: =IFERROR(D25/B25,0) -> 0.069998324
A26: Software | B26: =SUMIF(Raw_Data!E:E,A26,Raw_Data!G:G) -> 13490570 | C26: =SUMIF(Raw_Data!E:E,A26,Raw_Data!H:H) -> 13946100 | D26: =C26-B26 -> 455530 | E26: =IFERROR(D26/B26,0) -> 0.03376655
A27: Travel | B27: =SUMIF(Raw_Data!E:E,A27,Raw_Data!G:G) -> 14277603 | C27: =SUMIF(Raw_Data!E:E,A27,Raw_Data!H:H) -> 14969900 | D27: =C27-B27 -> 692297 | E27: =IFERROR(D27/B27,0) -> 0.048488321
A28: Marketing | B28: =SUMIF(Raw_Data!E:E,A28,Raw_Data!G:G) -> 14994471 | C28: =SUMIF(Raw_Data!E:E,A28,Raw_Data!H:H) -> 15921000 | D28: =C28-B28 -> 926529 | E28: =IFERROR(D28/B28,0) -> 0.061791376
A29: Office | B29: =SUMIF(Raw_Data!E:E,A29,Raw_Data!G:G) -> 15009243 | C29: =SUMIF(Raw_Data!E:E,A29,Raw_Data!H:H) -> 15651500 | D29: =C29-B29 -> 642257 | E29: =IFERROR(D29/B29,0) -> 0.042790766
A30: Consulting | B30: =SUMIF(Raw_Data!E:E,A30,Raw_Data!G:G) -> 13778240 | C30: =SUMIF(Raw_Data!E:E,A30,Raw_Data!H:H) -> 14662400 | D30: =C30-B30 -> 884160 | E30: =IFERROR(D30/B30,0) -> 0.06417075
A31: Training | B31: =SUMIF(Raw_Data!E:E,A31,Raw_Data!G:G) -> 15439582 | C31: =SUMIF(Raw_Data!E:E,A31,Raw_Data!H:H) -> 16486300 | D31: =C31-B31 -> 1046718 | E31: =IFERROR(D31/B31,0) -> 0.067794452
A32: Utilities | B32: =SUMIF(Raw_Data!E:E,A32,Raw_Data!G:G) -> 13206646 | C32: =SUMIF(Raw_Data!E:E,A32,Raw_Data!H:H) -> 13949500 | D32: =C32-B32 -> 742854 | E32: =IFERROR(D32/B32,0) -> 0.056248498
A36: Monthly Analysis
A37: Item | B37: Budget | C37: Actual | D37: Variance | E37: Variance %
A38: Jan | B38: =SUMIF(Raw_Data!C:C,A38,Raw_Data!G:G) -> 9078540 | C38: =SUMIF(Raw_Data!C:C,A38,Raw_Data!H:H) -> 9298600 | D38: =C38-B38 -> 220060 | E38: =IFERROR(D38/B38,0) -> 0.02423958
A39: Feb | B39: =SUMIF(Raw_Data!C:C,A39,Raw_Data!G:G) -> 9233322 | C39: =SUMIF(Raw_Data!C:C,A39,Raw_Data!H:H) -> 9817500 | D39: =C39-B39 -> 584178 | E39: =IFERROR(D39/B39,0) -> 0.063268453
A40: Mar | B40: =SUMIF(Raw_Data!C:C,A40,Raw_Data!G:G) -> 9338942 | C40: =SUMIF(Raw_Data!C:C,A40,Raw_Data!H:H) -> 10035000 | D40: =C40-B40 -> 696058 | E40: =IFERROR(D40/B40,0) -> 0.074532854
A41: Apr | B41: =SUMIF(Raw_Data!C:C,A41,Raw_Data!G:G) -> 9554799 | C41: =SUMIF(Raw_Data!C:C,A41,Raw_Data!H:H) -> 10116900 | D41: =C41-B41 -> 562101 | E41: =IFERROR(D41/B41,0) -> 0.058829181
A42: May | B42: =SUMIF(Raw_Data!C:C,A42,Raw_Data!G:G) -> 9631806 | C42: =SUMIF(Raw_Data!C:C,A42,Raw_Data!H:H) -> 10075700 | D42: =C42-B42 -> 443894 | E42: =IFERROR(D42/B42,0) -> 0.046086269
A43: Jun | B43: =SUMIF(Raw_Data!C:C,A43,Raw_Data!G:G) -> 8910827 | C43: =SUMIF(Raw_Data!C:C,A43,Raw_Data!H:H) -> 9444200 | D43: =C43-B43 -> 533373 | E43: =IFERROR(D43/B43,0) -> 0.059856734
A44: Jul | B44: =SUMIF(Raw_Data!C:C,A44,Raw_Data!G:G) -> 9149487 | C44: =SUMIF(Raw_Data!C:C,A44,Raw_Data!H:H) -> 9724600 | D44: =C44-B44 -> 575113 | E44: =IFERROR(D44/B44,0) -> 0.062857404
A45: Aug | B45: =SUMIF(Raw_Data!C:C,A45,Raw_Data!G:G) -> 9498907 | C45: =SUMIF(Raw_Data!C:C,A45,Raw_Data!H:H) -> 9900900 | D45: =C45-B45 -> 401993 | E45: =IFERROR(D45/B45,0) -> 0.042319922
A46: Sep | B46: =SUMIF(Raw_Data!C:C,A46,Raw_Data!G:G) -> 9910492 | C46: =SUMIF(Raw_Data!C:C,A46,Raw_Data!H:H) -> 10586500 | D46: =C46-B46 -> 676008 | E46: =IFERROR(D46/B46,0) -> 0.068211346
A47: Oct | B47: =SUMIF(Raw_Data!C:C,A47,Raw_Data!G:G) -> 9711348 | C47: =SUMIF(Raw_Data!C:C,A47,Raw_Data!H:H) -> 10119400 | D47: =C47-B47 -> 408052 | E47: =IFERROR(D47/B47,0) -> 0.04201806
A48: Nov | B48: =SUMIF(Raw_Data!C:C,A48,Raw_Data!G:G) -> 9941885 | C48: =SUMIF(Raw_Data!C:C,A48,Raw_Data!H:H) -> 10582500 | D48: =C48-B48 -> 640615 | E48: =IFERROR(D48/B48,0) -> 0.06443597
A49: Dec | B49: =SUMIF(Raw_Data!C:C,A49,Raw_Data!G:G) -> 9214525 | C49: =SUMIF(Raw_Data!C:C,A49,Raw_Data!H:H) -> 9771900 | D49: =C49-B49 -> 557375 | E49: =IFERROR(D49/B49,0) -> 0.060488739

Sheet Dashboard
A1: BUDGET VS ACTUAL | FINANCIAL PERFORMANCE DASHBOARD
A2: Synthetic FY2026 dataset • 1,000 transactions
A4: Total Budget | D4: Total Actual | G4: Total Variance | J4: Variance %
A5: =Analysis!B5 -> 113174880 | D5: =Analysis!B6 -> 119473700 | G5: =Analysis!B7 -> 6298820 | J5: =Analysis!B8 -> 0.055655637
G24: Management Notes
G25: • Positive variance = actual spend above budget (unfavorable for expense control).
G26: • Negative variance = actual spend below budget (favorable for expense control).
G27: • Investigate material variances by department, category, vendor and month.
G28: • The workbook uses synthetic data for portfolio/interview demonstration.

Sheet Formula_Guide
A1: Formula / Concept | B1: Excel Formula | C1: Purpose | D1: Interview explanation
A2: Total Budget | B2: =SUM(Raw_Data!G2:G1001) -> 113174880 | C2: Adds planned spend | D2: SUM calculates total budget across transactions.
A3: Total Actual | B3: =SUM(Raw_Data!H2:H1001) -> 119473700 | C3: Adds actual spend | D3: SUM calculates actual expenditure for the period.
A4: Variance | B4: =Actual-Budget -> #NAME? | C4: Measures budget gap | D4: Positive means actual exceeded budget; negative means actual was below budget.
A5: Variance % | B5: =IFERROR(Variance/Budget,0) -> 0 | C5: Normalizes variance | D5: Dividing variance by budget makes performance comparable across units.
A6: SUMIF | B6: =SUMIF(Range,_xlnm.Criteria,Sum_Range) -> #NAME? | C6: Aggregates by one condition | D6: I used SUMIF to summarize budget and actual by department, category and month.
A7: COUNTIF | B7: =COUNTIF(Range,_xlnm.Criteria) -> #NAME? | C7: Counts matching records | D7: I used COUNTIF to count favorable and unfavorable transactions.
A8: IFERROR | B8: =IFERROR(I2/G2,0) -> 0 | C8: Handles divide-by-zero | D8: It prevents errors when a budget is zero.
A9: SUMIFS | C9: Multi-condition aggregation | D9: I would use SUMIFS when I need to filter by multiple dimensions, such as department and month.

Sheet README
A1: PROJECT README — BUDGET VS ACTUAL FINANCIAL ANALYSIS
A3: Business Problem | B3: Analyze planned versus actual expenditure and identify the drivers of material variances.
A4: Dataset | B4: 1,000 synthetic FY2026 transactions across 6 departments, 8 expense categories and 10 vendors.
A5: Tools | B5: Excel formulas, conditional formatting, charts and dashboarding.
A6: Methodology | B6: Calculate Actual − Budget and Variance %, summarize by department/category/month, then identify material drivers.
A7: Interview Summary | B7: I built a budget-versus-actual model, analyzed variances across business dimensions, and created a management dashboard to support cost analysis.
A8: Data Note | B8: All transaction data in this workbook is synthetic and intended for learning, portfolio and interview demonstration.
