Workbook

Sheet README
A1: Project 4 — AP & Working Capital Analytics
A3: Objective | B3: Analyze Accounts Payable, invoice aging, payment performance, vendor concentration and working-capital implications.
A4: Dataset | B4: 1,000 synthetic AP invoices created for portfolio practice.
A5: As-of date | B5: 31-Dec-2026 for outstanding/aging analysis.
A6: Tools | B6: Excel + SQL + Power BI-ready dataset.
A7: Core workflow | B7: Raw invoices → calculated fields → aging → vendor/department analysis → working capital → dashboard → insights.
A8: Important | B8: This is a portfolio simulation, not actual employer/client data. Do not present synthetic results as real company results.
A9: DPO note | B9: The workbook includes an illustrative DPO methodology using average AP / assumed annual purchases. Replace the assumption with actual COGS/purchases when available.
A12: Workbook map
A13: • Raw_Data
A14: • Calculated_Fields
A15: • Aging_Analysis
A16: • Vendor_Analysis
A17: • Department_Analysis
A18: • Working_Capital
A19: • Dashboard
A20: • Insights
A21: • Sources
A22: • Reverse_Engineering

Sheet Raw_Data
A1: Raw AP Invoice Dataset
A3: Invoice_ID | B3: Invoice_Date | C3: Vendor | D3: Department | E3: Category | F3: Invoice_Amount | G3: Payment_Terms_Days | H3: Due_Date | I3: Payment_Date | J3: Payment_Status | K3: Discount_Available | L3: Discount_% | M3: GRN_Status | N3: Approval_Status
A4: INV00001 | B4: 46330 | C4: Microsoft | D4: Sales | E4: Consulting | F4: 59700 | G4: 30 | H4: 46360 | I4: 46360 | J4: Paid | K4: Yes | L4: 0.02 | M4: Received | N4: Approved
A5: INV00002 | B5: 46272 | C5: Wipro | D5: Sales | E5: Travel | F5: 59000 | G5: 60 | H5: 46332 | J5: Pending | K5: Yes | L5: 0.02 | M5: Received | N5: Approved
A6: INV00003 | B6: 46137 | C6: Oracle | D6: IT | E6: Software | F6: 885600 | G6: 60 | H6: 46197 | J6: Pending | K6: No | L6: 0 | M6: Received | N6: Pending
A7: INV00004 | B7: 46206 | C7: Google Cloud | D7: HR | E7: Facilities | F7: 146500 | G7: 45 | H7: 46251 | I7: 46266 | J7: Paid | K7: No | L7: 0 | M7: Received | N7: Approved
A8: INV00005 | B8: 46212 | C8: IBM | D8: Sales | E8: Facilities | F8: 516500 | G8: 45 | H8: 46257 | I8: 46262 | J8: Paid | K8: Yes | L8: 0.02 | M8: Received | N8: Approved
A9: INV00006 | B9: 46118 | C9: IBM | D9: Operations | E9: Consulting | F9: 172700 | G9: 30 | H9: 46148 | I9: 46148 | J9: Paid | K9: Yes | L9: 0.02 | M9: Received | N9: Approved
A10: INV00007 | B10: 46318 | C10: Oracle | D10: Finance | E10: Travel | F10: 935900 | G10: 60 | H10: 46378 | I10: 46378 | J10: Paid | K10: No | L10: 0 | M10: Received | N10: Approved
A11: INV00008 | B11: 46222 | C11: Adobe | D11: HR | E11: Cloud | F11: 129800 | G11: 30 | H11: 46252 | J11: Pending | K11: Yes | L11: 0.02 | M11: Received | N11: Approved
A12: INV00009 | B12: 46298 | C12: Adobe | D12: Operations | E12: Office Supplies | F12: 134600 | G12: 60 | H12: 46358 | I12: 46358 | J12: Paid | K12: No | L12: 0 | M12: Received | N12: Approved
A13: INV00010 | B13: 46177 | C13: Infosys | D13: Operations | E13: Cloud | F13: 791600 | G13: 60 | H13: 46237 | J13: Pending | K13: No | L13: 0 | M13: Received | N13: Approved
A14: INV00011 | B14: 46336 | C14: HCLTech | D14: Sales | E14: Office Supplies | F14: 42400 | G14: 30 | H14: 46366 | I14: 46366 | J14: Paid | K14: Yes | L14: 0.02 | M14: Received | N14: Pending
A15: INV00012 | B15: 46150 | C15: Microsoft | D15: Finance | E15: Office Supplies | F15: 26000 | G15: 15 | H15: 46165 | J15: Pending | K15: No | L15: 0 | M15: Received | N15: Approved
A16: INV00013 | B16: 46271 | C16: Infosys | D16: Marketing | E16: Facilities | F16: 241300 | G16: 60 | H16: 46331 | I16: 46331 | J16: Paid | K16: No | L16: 0 | M16: Received | N16: Approved
A17: INV00014 | B17: 46238 | C17: TCS | D17: Finance | E17: Software | F17: 10200 | G17: 45 | H17: 46283 | I17: 46298 | J17: Paid | K17: Yes | L17: 0.02 | M17: Received | N17: Approved
A18: INV00015 | B18: 46176 | C18: Google Cloud | D18: Finance | E18: Consulting | F18: 349200 | G18: 60 | H18: 46236 | I18: 46236 | J18: Paid | K18: No | L18: 0 | M18: Received | N18: Approved
A19: INV00016 | B19: 46187 | C19: Adobe | D19: Operations | E19: Facilities | F19: 170000 | G19: 15 | H19: 46202 | I19: 46217 | J19: Paid | K19: No | L19: 0 | M19: Received | N19: Approved
A20: INV00017 | B20: 46280 | C20: Deloitte | D20: Operations | E20: Cloud | F20: 118300 | G20: 45 | H20: 46325 | I20: 46355 | J20: Paid | K20: No | L20: 0 | M20: Received | N20: Pending
A21: INV00018 | B21: 46025 | C21: Zoho | D21: Finance | E21: Cloud | F21: 410300 | G21: 60 | H21: 46085 | J21: Pending | K21: Yes | L21: 0.02 | M21: Received | N21: Approved
A22: INV00019 | B22: 46244 | C22: Adobe | D22: Sales | E22: Travel | F22: 42900 | G22: 60 | H22: 46304 | I22: 46304 | J22: Paid | K22: No | L22: 0 | M22: Received | N22: Approved
A23: INV00020 | B23: 46293 | C23: Google Cloud | D23: Finance | E23: Software | F23: 213600 | G23: 15 | H23: 46308 | I23: 46308 | J23: Paid | K23: Yes | L23: 0.02 | M23: Pending | N23: Approved
A24: INV00021 | B24: 46297 | C24: Accenture | D24: IT | E24: Professional Services | F24: 403200 | G24: 45 | H24: 46342 | I24: 46342 | J24: Paid | K24: No | L24: 0 | M24: Received | N24: Approved
A25: INV00022 | B25: 46054 | C25: IBM | D25: Marketing | E25: Office Supplies | F25: 409900 | G25: 15 | H25: 46069 | I25: 46069 | J25: Paid | K25: Yes | L25: 0.02 | M25: Received | N25: Approved
A26: INV00023 | B26: 46261 | C26: Google Cloud | D26: Sales | E26: Consulting | F26: 168600 | G26: 15 | H26: 46276 | J26: Pending | K26: Yes | L26: 0.02 | M26: Received | N26: Approved
A27: INV00024 | B27: 46270 | C27: Infosys | D27: HR | E27: Office Supplies | F27: 402700 | G27: 30 | H27: 46300 | I27: 46300 | J27: Paid | K27: No | L27: 0 | M27: Received | N27: Approved
A28: INV00025 | B28: 46144 | C28: Microsoft | D28: HR | E28: Facilities | F28: 446500 | G28: 30 | H28: 46174 | I28: 46174 | J28: Paid | K28: Yes | L28: 0.02 | M28: Received | N28: Approved
A29: INV00026 | B29: 46099 | C29: Microsoft | D29: HR | E29: Office Supplies | F29: 281400 | G29: 30 | H29: 46129 | J29: Pending | K29: No | L29: 0 | M29: Received | N29: Approved
A30: INV00027 | B30: 46134 | C30: TCS | D30: Sales | E30: Software | F30: 913100 | G30: 45 | H30: 46179 | J30: Pending | K30: No | L30: 0 | M30: Pending | N30: Approved
A31: INV00028 | B31: 46107 | C31: Cognizant | D31: Finance | E31: Professional Services | F31: 943400 | G31: 15 | H31: 46122 | J31: Pending | K31: No | L31: 0 | M31: Received | N31: Approved
A32: INV00029 | B32: 46360 | C32: Adobe | D32: IT | E32: Facilities | F32: 862400 | G32: 60 | H32: 46420 | I32: 46450 | J32: Paid | K32: No | L32: 0 | M32: Received | N32: Approved
A33: INV00030 | B33: 46214 | C33: Infosys | D33: IT | E33: Facilities | F33: 632100 | G33: 45 | H33: 46259 | J33: Pending | K33: Yes | L33: 0.02 | M33: Pending | N33: Approved
A34: INV00031 | B34: 46144 | C34: Amazon Web Services | D34: Marketing | E34: Professional Services | F34: 183500 | G34: 45 | H34: 46189 | I34: 46194 | J34: Paid | K34: Yes | L34: 0.02 | M34: Received | N34: Approved
A35: INV00032 | B35: 46287 | C35: Wipro | D35: Sales | E35: Travel | F35: 302500 | G35: 30 | H35: 46317 | I35: 46322 | J35: Paid | K35: Yes | L35: 0.02 | M35: Pending | N35: Approved
A36: INV00033 | B36: 46340 | C36: Oracle | D36: Operations | E36: Travel | F36: 393900 | G36: 45 | H36: 46385 | I36: 46445 | J36: Paid | K36: No | L36: 0 | M36: Received | N36: Approved
A37: INV00034 | B37: 46032 | C37: Infosys | D37: Finance | E37: Professional Services | F37: 118900 | G37: 45 | H37: 46077 | I37: 46092 | J37: Paid | K37: No | L37: 0 | M37: Received | N37: Approved
A38: INV00035 | B38: 46159 | C38: SAP | D38: Sales | E38: Office Supplies | F38: 27900 | G38: 45 | H38: 46204 | I38: 46204 | J38: Paid | K38: Yes | L38: 0.02 | M38: Received | N38: Approved
A39: INV00036 | B39: 46254 | C39: HCLTech | D39: IT | E39: Professional Services | F39: 681800 | G39: 60 | H39: 46314 | I39: 46314 | J39: Paid | K39: No | L39: 0 | M39: Received | N39: Approved
A40: INV00037 | B40: 46078 | C40: Adobe | D40: Finance | E40: Cloud | F40: 17300 | G40: 60 | H40: 46138 | I40: 46168 | J40: Paid | K40: No | L40: 0 | M40: Pending | N40: Approved
A41: INV00038 | B41: 46254 | C41: HCLTech | D41: Sales | E41: Office Supplies | F41: 208500 | G41: 60 | H41: 46314 | J41: Pending | K41: No | L41: 0 | M41: Received | N41: Approved
A42: INV00039 | B42: 46335 | C42: Cognizant | D42: Marketing | E42: Professional Services | F42: 308100 | G42: 30 | H42: 46365 | I42: 46365 | J42: Paid | K42: No | L42: 0 | M42: Received | N42: Approved
A43: INV00040 | B43: 46226 | C43: Deloitte | D43: Sales | E43: Cloud | F43: 498200 | G43: 15 | H43: 46241 | I43: 46241 | J43: Paid | K43: No | L43: 0 | M43: Pending | N43: Approved
A44: INV00041 | B44: 46357 | C44: HCLTech | D44: Marketing | E44: Professional Services | F44: 513800 | G44: 60 | H44: 46417 | J44: Pending | K44: No | L44: 0 | M44: Received | N44: Approved
A45: INV00042 | B45: 46291 | C45: Accenture | D45: Finance | E45: Professional Services | F45: 614200 | G45: 30 | H45: 46321 | I45: 46326 | J45: Paid | K45: No | L45: 0 | M45: Received | N45: Approved
A46: INV00043 | B46: 46101 | C46: Google Cloud | D46: IT | E46: Professional Services | F46: 571500 | G46: 15 | H46: 46116 | I46: 46116 | J46: Paid | K46: Yes | L46: 0.02 | M46: Received | N46: Approved
A47: INV00044 | B47: 46212 | C47: Cognizant | D47: Operations | E47: Consulting | F47: 120200 | G47: 15 | H47: 46227 | J47: Pending | K47: Yes | L47: 0.02 | M47: Received | N47: Approved
A48: INV00045 | B48: 46328 | C48: Cognizant | D48: IT | E48: Cloud | F48: 210600 | G48: 30 | H48: 46358 | I48: 46363 | J48: Paid | K48: No | L48: 0 | M48: Received | N48: Approved
A49: INV00046 | B49: 46179 | C49: Accenture | D49: Marketing | E49: Travel | F49: 372800 | G49: 15 | H49: 46194 | I49: 46194 | J49: Paid | K49: Yes | L49: 0.02 | M49: Received | N49: Pending
A50: INV00047 | B50: 46226 | C50: TCS | D50: IT | E50: Office Supplies | F50: 30000 | G50: 30 | H50: 46256 | J50: Pending | K50: No | L50: 0 | M50: Received | N50: Approved
A51: INV00048 | B51: 46338 | C51: Amazon Web Services | D51: Marketing | E51: Travel | F51: 565000 | G51: 45 | H51: 46383 | I51: 46473 | J51: Paid | K51: No | L51: 0 | M51: Received | N51: Approved
A52: INV00049 | B52: 46209 | C52: Wipro | D52: Marketing | E52: Travel | F52: 939700 | G52: 45 | H52: 46254 | I52: 46284 | J52: Paid | K52: No | L52: 0 | M52: Received | N52: Approved
A53: INV00050 | B53: 46062 | C53: Zoho | D53: Operations | E53: Cloud | F53: 751100 | G53: 60 | H53: 46122 | I53: 46152 | J53: Paid | K53: Yes | L53: 0.02 | M53: Received | N53: Approved
A54: INV00051 | B54: 46182 | C54: Zoho | D54: Marketing | E54: Travel | F54: 141200 | G54: 45 | H54: 46227 | I54: 46242 | J54: Paid | K54: No | L54: 0 | M54: Received | N54: Approved
A55: INV00052 | B55: 46349 | C55: IBM | D55: Operations | E55: Facilities | F55: 27800 | G55: 15 | H55: 46364 | I55: 46369 | J55: Paid | K55: No | L55: 0 | M55: Received | N55: Approved
A56: INV00053 | B56: 46374 | C56: Oracle | D56: HR | E56: Travel | F56: 71400 | G56: 60 | H56: 46434 | J56: Pending | K56: Yes | L56: 0.02 | M56: Received | N56: Pending
A57: INV00054 | B57: 46362 | C57: TCS | D57: Finance | E57: Travel | F57: 692200 | G57: 60 | H57: 46422 | J57: Pending | K57: No | L57: 0 | M57: Received | N57: Approved
A58: INV00055 | B58: 46143 | C58: Wipro | D58: Marketing | E58: Cloud | F58: 290900 | G58: 45 | H58: 46188 | I58: 46188 | J58: Paid | K58: No | L58: 0 | M58: Received | N58: Approved
A59: INV00056 | B59: 46305 | C59: IBM | D59: Operations | E59: Professional Services | F59: 288500 | G59: 45 | H59: 46350 | I59: 46350 | J59: Paid | K59: No | L59: 0 | M59: Received | N59: Approved
A60: INV00057 | B60: 46086 | C60: Cognizant | D60: Marketing | E60: Consulting | F60: 338800 | G60: 15 | H60: 46101 | I60: 46116 | J60: Paid | K60: Yes | L60: 0.02 | M60: Received | N60: Approved
A61: INV00058 | B61: 46244 | C61: HCLTech | D61: Marketing | E61: Professional Services | F61: 144300 | G61: 45 | H61: 46289 | J61: Pending | K61: Yes | L61: 0.02 | M61: Received | N61: Approved
A62: INV00059 | B62: 46089 | C62: Deloitte | D62: Marketing | E62: Software | F62: 587900 | G62: 30 | H62: 46119 | I62: 46119 | J62: Paid | K62: No | L62: 0 | M62: Received | N62: Approved
A63: INV00060 | B63: 46334 | C63: Zoho | D63: HR | E63: Facilities | F63: 109200 | G63: 30 | H63: 46364 | J63: Pending | K63: No | L63: 0 | M63: Received | N63: Approved
A64: INV00061 | B64: 46162 | C64: Wipro | D64: Marketing | E64: Consulting | F64: 766500 | G64: 60 | H64: 46222 | J64: Pending | K64: No | L64: 0 | M64: Received | N64: Approved
A65: INV00062 | B65: 46036 | C65: Wipro | D65: HR | E65: Office Supplies | F65: 11300 | G65: 45 | H65: 46081 | J65: Pending | K65: No | L65: 0 | M65: Received | N65: Approved
A66: INV00063 | B66: 46097 | C66: Google Cloud | D66: Sales | E66: Professional Services | F66: 689000 | G66: 45 | H66: 46142 | J66: Pending | K66: No | L66: 0 | M66: Received | N66: Approved
A67: INV00064 | B67: 46081 | C67: Deloitte | D67: HR | E67: Professional Services | F67: 75600 | G67: 60 | H67: 46141 | I67: 46141 | J67: Paid | K67: Yes | L67: 0.02 | M67: Pending | N67: Approved
A68: INV00065 | B68: 46292 | C68: Microsoft | D68: Sales | E68: Facilities | F68: 390700 | G68: 60 | H68: 46352 | I68: 46352 | J68: Paid | K68: No | L68: 0 | M68: Received | N68: Approved
A69: INV00066 | B69: 46091 | C69: IBM | D69: Sales | E69: Professional Services | F69: 12100 | G69: 15 | H69: 46106 | I69: 46106 | J69: Paid | K69: Yes | L69: 0.02 | M69: Received | N69: Approved
A70: INV00067 | B70: 46068 | C70: Amazon Web Services | D70: Sales | E70: Facilities | F70: 787500 | G70: 30 | H70: 46098 | I70: 46098 | J70: Paid | K70: No | L70: 0 | M70: Received | N70: Approved
A71: INV00068 | B71: 46132 | C71: Google Cloud | D71: Sales | E71: Cloud | F71: 842500 | G71: 15 | H71: 46147 | I71: 46162 | J71: Paid | K71: Yes | L71: 0.02 | M71: Received | N71: Approved
A72: INV00069 | B72: 46314 | C72: SAP | D72: Operations | E72: Facilities | F72: 613300 | G72: 30 | H72: 46344 | I72: 46344 | J72: Paid | K72: No | L72: 0 | M72: Received | N72: Approved
A73: INV00070 | B73: 46364 | C73: Accenture | D73: Operations | E73: Cloud | F73: 808500 | G73: 60 | H73: 46424 | I73: 46429 | J73: Paid | K73: No | L73: 0 | M73: Pending | N73: Approved
A74: INV00071 | B74: 46027 | C74: Google Cloud | D74: Marketing | E74: Consulting | F74: 580200 | G74: 15 | H74: 46042 | I74: 46042 | J74: Paid | K74: No | L74: 0 | M74: Pending | N74: Approved
A75: INV00072 | B75: 46153 | C75: Accenture | D75: Sales | E75: Professional Services | F75: 889300 | G75: 15 | H75: 46168 | J75: Pending | K75: No | L75: 0 | M75: Pending | N75: Approved
A76: INV00073 | B76: 46267 | C76: Accenture | D76: IT | E76: Cloud | F76: 810100 | G76: 45 | H76: 46312 | J76: Pending | K76: No | L76: 0 | M76: Received | N76: Approved
A77: INV00074 | B77: 46104 | C77: Infosys | D77: IT | E77: Software | F77: 470000 | G77: 45 | H77: 46149 | I77: 46149 | J77: Paid | K77: No | L77: 0 | M77: Received | N77: Approved
A78: INV00075 | B78: 46084 | C78: Accenture | D78: Operations | E78: Office Supplies | F78: 126900 | G78: 30 | H78: 46114 | I78: 46114 | J78: Paid | K78: Yes | L78: 0.02 | M78: Received | N78: Approved
A79: INV00076 | B79: 46164 | C79: Google Cloud | D79: Finance | E79: Software | F79: 990700 | G79: 60 | H79: 46224 | I79: 46224 | J79: Paid | K79: Yes | L79: 0.02 | M79: Received | N79: Approved
A80: INV00077 | B80: 46231 | C80: IBM | D80: IT | E80: Cloud | F80: 681100 | G80: 60 | H80: 46291 | I80: 46321 | J80: Paid | K80: No | L80: 0 | M80: Received | N80: Approved
A81: INV00078 | B81: 46358 | C81: Zoho | D81: Marketing | E81: Travel | F81: 209000 | G81: 60 | H81: 46418 | I81: 46418 | J81: Paid | K81: No | L81: 0 | M81: Received | N81: Approved
A82: INV00079 | B82: 46381 | C82: SAP | D82: Sales | E82: Facilities | F82: 158900 | G82: 30 | H82: 46411 | I82: 46411 | J82: Paid | K82: No | L82: 0 | M82: Received | N82: Approved
A83: INV00080 | B83: 46153 | C83: Wipro | D83: Operations | E83: Cloud | F83: 654600 | G83: 30 | H83: 46183 | I83: 46243 | J83: Paid | K83: No | L83: 0 | M83: Received | N83: Approved
A84: INV00081 | B84: 46260 | C84: Infosys | D84: Sales | E84: Facilities | F84: 202000 | G84: 45 | H84: 46305 | I84: 46395 | J84: Paid | K84: No | L84: 0 | M84: Received | N84: Pending
A85: INV00082 | B85: 46277 | C85: Amazon Web Services | D85: Operations | E85: Software | F85: 591100 | G85: 45 | H85: 46322 | I85: 46352 | J85: Paid | K85: No | L85: 0 | M85: Received | N85: Approved
A86: INV00083 | B86: 46042 | C86: Zoho | D86: Marketing | E86: Consulting | F86: 726600 | G86: 30 | H86: 46072 | J86: Pending | K86: Yes | L86: 0.02 | M86: Received | N86: Approved
A87: INV00084 | B87: 46032 | C87: IBM | D87: IT | E87: Software | F87: 351700 | G87: 30 | H87: 46062 | I87: 46122 | J87: Paid | K87: No | L87: 0 | M87: Received | N87: Approved
A88: INV00085 | B88: 46361 | C88: Zoho | D88: Operations | E88: Travel | F88: 711700 | G88: 15 | H88: 46376 | I88: 46376 | J88: Paid | K88: No | L88: 0 | M88: Pending | N88: Approved
A89: INV00086 | B89: 46075 | C89: Oracle | D89: Marketing | E89: Travel | F89: 19800 | G89: 45 | H89: 46120 | J89: Pending | K89: No | L89: 0 | M89: Received | N89: Approved
A90: INV00087 | B90: 46346 | C90: Microsoft | D90: IT | E90: Facilities | F90: 64700 | G90: 45 | H90: 46391 | I90: 46406 | J90: Paid | K90: Yes | L90: 0.02 | M90: Received | N90: Approved
A91: INV00088 | B91: 46198 | C91: Deloitte | D91: Marketing | E91: Software | F91: 215300 | G91: 45 | H91: 46243 | I91: 46258 | J91: Paid | K91: Yes | L91: 0.02 | M91: Received | N91: Approved
A92: INV00089 | B92: 46199 | C92: Cognizant | D92: Finance | E92: Office Supplies | F92: 8900 | G92: 45 | H92: 46244 | J92: Pending | K92: No | L92: 0 | M92: Received | N92: Approved
A93: INV00090 | B93: 46190 | C93: Accenture | D93: IT | E93: Professional Services | F93: 282500 | G93: 30 | H93: 46220 | I93: 46310 | J93: Paid | K93: Yes | L93: 0.02 | M93: Received | N93: Approved
A94: INV00091 | B94: 46330 | C94: IBM | D94: Sales | E94: Professional Services | F94: 225300 | G94: 15 | H94: 46345 | I94: 46345 | J94: Paid | K94: No | L94: 0 | M94: Received | N94: Approved
A95: INV00092 | B95: 46312 | C95: Infosys | D95: Operations | E95: Office Supplies | F95: 29300 | G95: 60 | H95: 46372 | I95: 46432 | J95: Paid | K95: No | L95: 0 | M95: Received | N95: Approved
A96: INV00093 | B96: 46360 | C96: Oracle | D96: Operations | E96: Consulting | F96: 364500 | G96: 45 | H96: 46405 | I96: 46435 | J96: Paid | K96: Yes | L96: 0.02 | M96: Received | N96: Approved
A97: INV00094 | B97: 46099 | C97: Microsoft | D97: Marketing | E97: Office Supplies | F97: 558100 | G97: 45 | H97: 46144 | J97: Pending | K97: No | L97: 0 | M97: Pending | N97: Approved
A98: INV00095 | B98: 46177 | C98: Accenture | D98: Marketing | E98: Cloud | F98: 165900 | G98: 30 | H98: 46207 | I98: 46212 | J98: Paid | K98: Yes | L98: 0.02 | M98: Received | N98: Approved
A99: INV00096 | B99: 46231 | C99: Google Cloud | D99: Marketing | E99: Office Supplies | F99: 743400 | G99: 15 | H99: 46246 | I99: 46246 | J99: Paid | K99: No | L99: 0 | M99: Pending | N99: Approved
A100: INV00097 | B100: 46109 | C100: Deloitte | D100: Marketing | E100: Travel | F100: 22000 | G100: 60 | H100: 46169 | I100: 46169 | J100: Paid | K100: No | L100: 0 | M100: Received | N100: Approved
A101: INV00098 | B101: 46166 | C101: Oracle | D101: Marketing | E101: Office Supplies | F101: 221400 | G101: 15 | H101: 46181 | I101: 46181 | J101: Paid | K101: No | L101: 0 | M101: Received | N101: Approved
...

Sheet Calculated_Fields
A1: Calculated AP Metrics
A3: Invoice_ID | B3: Invoice_Date | C3: Vendor | D3: Department | E3: Invoice_Amount | F3: Due_Date | G3: Payment_Date | H3: Status | I3: Payment_Days | J3: Days_Past_Due | K3: Outstanding_Amount | L3: Aging_Bucket | M3: Discount_Opportunity | N3: Payment_Timing
A4: =Raw_Data!A4 | B4: =Raw_Data!B4 | C4: =Raw_Data!C4 | D4: =Raw_Data!D4 | E4: =Raw_Data!F4 | F4: =Raw_Data!H4 | G4: =Raw_Data!I4 | H4: =Raw_Data!J4 | I4: =IF(G4="",0,G4-B4) | J4: =IF(H4="Paid",MAX(0,G4-F4),MAX(0,DATE(2026,12,31)-F4)) | K4: =IF(H4="Paid",0,E4) | L4: =IF(J4=0,"Current",IF(J4<=30,"1-30 Days",IF(J4<=60,"31-60 Days",IF(J4<=90,"61-90 Days","90+ Days")))) | M4: =IF(Raw_Data!K4="Yes",Raw_Data!F4*Raw_Data!L4,0) | N4: =IF(H4<>"Paid","Outstanding",IF(J4=0,"On Time","Late"))
A5: =Raw_Data!A5 | B5: =Raw_Data!B5 | C5: =Raw_Data!C5 | D5: =Raw_Data!D5 | E5: =Raw_Data!F5 | F5: =Raw_Data!H5 | G5: =Raw_Data!I5 | H5: =Raw_Data!J5 | I5: =IF(G5="",0,G5-B5) | J5: =IF(H5="Paid",MAX(0,G5-F5),MAX(0,DATE(2026,12,31)-F5)) | K5: =IF(H5="Paid",0,E5) | L5: =IF(J5=0,"Current",IF(J5<=30,"1-30 Days",IF(J5<=60,"31-60 Days",IF(J5<=90,"61-90 Days","90+ Days")))) | M5: =IF(Raw_Data!K5="Yes",Raw_Data!F5*Raw_Data!L5,0) | N5: =IF(H5<>"Paid","Outstanding",IF(J5=0,"On Time","Late"))
A6: =Raw_Data!A6 | B6: =Raw_Data!B6 | C6: =Raw_Data!C6 | D6: =Raw_Data!D6 | E6: =Raw_Data!F6 | F6: =Raw_Data!H6 | G6: =Raw_Data!I6 | H6: =Raw_Data!J6 | I6: =IF(G6="",0,G6-B6) | J6: =IF(H6="Paid",MAX(0,G6-F6),MAX(0,DATE(2026,12,31)-F6)) | K6: =IF(H6="Paid",0,E6) | L6: =IF(J6=0,"Current",IF(J6<=30,"1-30 Days",IF(J6<=60,"31-60 Days",IF(J6<=90,"61-90 Days","90+ Days")))) | M6: =IF(Raw_Data!K6="Yes",Raw_Data!F6*Raw_Data!L6,0) | N6: =IF(H6<>"Paid","Outstanding",IF(J6=0,"On Time","Late"))
A7: =Raw_Data!A7 | B7: =Raw_Data!B7 | C7: =Raw_Data!C7 | D7: =Raw_Data!D7 | E7: =Raw_Data!F7 | F7: =Raw_Data!H7 | G7: =Raw_Data!I7 | H7: =Raw_Data!J7 | I7: =IF(G7="",0,G7-B7) | J7: =IF(H7="Paid",MAX(0,G7-F7),MAX(0,DATE(2026,12,31)-F7)) | K7: =IF(H7="Paid",0,E7) | L7: =IF(J7=0,"Current",IF(J7<=30,"1-30 Days",IF(J7<=60,"31-60 Days",IF(J7<=90,"61-90 Days","90+ Days")))) | M7: =IF(Raw_Data!K7="Yes",Raw_Data!F7*Raw_Data!L7,0) | N7: =IF(H7<>"Paid","Outstanding",IF(J7=0,"On Time","Late"))
A8: =Raw_Data!A8 | B8: =Raw_Data!B8 | C8: =Raw_Data!C8 | D8: =Raw_Data!D8 | E8: =Raw_Data!F8 | F8: =Raw_Data!H8 | G8: =Raw_Data!I8 | H8: =Raw_Data!J8 | I8: =IF(G8="",0,G8-B8) | J8: =IF(H8="Paid",MAX(0,G8-F8),MAX(0,DATE(2026,12,31)-F8)) | K8: =IF(H8="Paid",0,E8) | L8: =IF(J8=0,"Current",IF(J8<=30,"1-30 Days",IF(J8<=60,"31-60 Days",IF(J8<=90,"61-90 Days","90+ Days")))) | M8: =IF(Raw_Data!K8="Yes",Raw_Data!F8*Raw_Data!L8,0) | N8: =IF(H8<>"Paid","Outstanding",IF(J8=0,"On Time","Late"))
A9: =Raw_Data!A9 | B9: =Raw_Data!B9 | C9: =Raw_Data!C9 | D9: =Raw_Data!D9 | E9: =Raw_Data!F9 | F9: =Raw_Data!H9 | G9: =Raw_Data!I9 | H9: =Raw_Data!J9 | I9: =IF(G9="",0,G9-B9) | J9: =IF(H9="Paid",MAX(0,G9-F9),MAX(0,DATE(2026,12,31)-F9)) | K9: =IF(H9="Paid",0,E9) | L9: =IF(J9=0,"Current",IF(J9<=30,"1-30 Days",IF(J9<=60,"31-60 Days",IF(J9<=90,"61-90 Days","90+ Days")))) | M9: =IF(Raw_Data!K9="Yes",Raw_Data!F9*Raw_Data!L9,0) | N9: =IF(H9<>"Paid","Outstanding",IF(J9=0,"On Time","Late"))
A10: =Raw_Data!A10 | B10: =Raw_Data!B10 | C10: =Raw_Data!C10 | D10: =Raw_Data!D10 | E10: =Raw_Data!F10 | F10: =Raw_Data!H10 | G10: =Raw_Data!I10 | H10: =Raw_Data!J10 | I10: =IF(G10="",0,G10-B10) | J10: =IF(H10="Paid",MAX(0,G10-F10),MAX(0,DATE(2026,12,31)-F10)) | K10: =IF(H10="Paid",0,E10) | L10: =IF(J10=0,"Current",IF(J10<=30,"1-30 Days",IF(J10<=60,"31-60 Days",IF(J10<=90,"61-90 Days","90+ Days")))) | M10: =IF(Raw_Data!K10="Yes",Raw_Data!F10*Raw_Data!L10,0) | N10: =IF(H10<>"Paid","Outstanding",IF(J10=0,"On Time","Late"))
A11: =Raw_Data!A11 | B11: =Raw_Data!B11 | C11: =Raw_Data!C11 | D11: =Raw_Data!D11 | E11: =Raw_Data!F11 | F11: =Raw_Data!H11 | G11: =Raw_Data!I11 | H11: =Raw_Data!J11 | I11: =IF(G11="",0,G11-B11) | J11: =IF(H11="Paid",MAX(0,G11-F11),MAX(0,DATE(2026,12,31)-F11)) | K11: =IF(H11="Paid",0,E11) | L11: =IF(J11=0,"Current",IF(J11<=30,"1-30 Days",IF(J11<=60,"31-60 Days",IF(J11<=90,"61-90 Days","90+ Days")))) | M11: =IF(Raw_Data!K11="Yes",Raw_Data!F11*Raw_Data!L11,0) | N11: =IF(H11<>"Paid","Outstanding",IF(J11=0,"On Time","Late"))
A12: =Raw_Data!A12 | B12: =Raw_Data!B12 | C12: =Raw_Data!C12 | D12: =Raw_Data!D12 | E12: =Raw_Data!F12 | F12: =Raw_Data!H12 | G12: =Raw_Data!I12 | H12: =Raw_Data!J12 | I12: =IF(G12="",0,G12-B12) | J12: =IF(H12="Paid",MAX(0,G12-F12),MAX(0,DATE(2026,12,31)-F12)) | K12: =IF(H12="Paid",0,E12) | L12: =IF(J12=0,"Current",IF(J12<=30,"1-30 Days",IF(J12<=60,"31-60 Days",IF(J12<=90,"61-90 Days","90+ Days")))) | M12: =IF(Raw_Data!K12="Yes",Raw_Data!F12*Raw_Data!L12,0) | N12: =IF(H12<>"Paid","Outstanding",IF(J12=0,"On Time","Late"))
A13: =Raw_Data!A13 | B13: =Raw_Data!B13 | C13: =Raw_Data!C13 | D13: =Raw_Data!D13 | E13: =Raw_Data!F13 | F13: =Raw_Data!H13 | G13: =Raw_Data!I13 | H13: =Raw_Data!J13 | I13: =IF(G13="",0,G13-B13) | J13: =IF(H13="Paid",MAX(0,G13-F13),MAX(0,DATE(2026,12,31)-F13)) | K13: =IF(H13="Paid",0,E13) | L13: =IF(J13=0,"Current",IF(J13<=30,"1-30 Days",IF(J13<=60,"31-60 Days",IF(J13<=90,"61-90 Days","90+ Days")))) | M13: =IF(Raw_Data!K13="Yes",Raw_Data!F13*Raw_Data!L13,0) | N13: =IF(H13<>"Paid","Outstanding",IF(J13=0,"On Time","Late"))
A14: =Raw_Data!A14 | B14: =Raw_Data!B14 | C14: =Raw_Data!C14 | D14: =Raw_Data!D14 | E14: =Raw_Data!F14 | F14: =Raw_Data!H14 | G14: =Raw_Data!I14 | H14: =Raw_Data!J14 | I14: =IF(G14="",0,G14-B14) | J14: =IF(H14="Paid",MAX(0,G14-F14),MAX(0,DATE(2026,12,31)-F14)) | K14: =IF(H14="Paid",0,E14) | L14: =IF(J14=0,"Current",IF(J14<=30,"1-30 Days",IF(J14<=60,"31-60 Days",IF(J14<=90,"61-90 Days","90+ Days")))) | M14: =IF(Raw_Data!K14="Yes",Raw_Data!F14*Raw_Data!L14,0) | N14: =IF(H14<>"Paid","Outstanding",IF(J14=0,"On Time","Late"))
A15: =Raw_Data!A15 | B15: =Raw_Data!B15 | C15: =Raw_Data!C15 | D15: =Raw_Data!D15 | E15: =Raw_Data!F15 | F15: =Raw_Data!H15 | G15: =Raw_Data!I15 | H15: =Raw_Data!J15 | I15: =IF(G15="",0,G15-B15) | J15: =IF(H15="Paid",MAX(0,G15-F15),MAX(0,DATE(2026,12,31)-F15)) | K15: =IF(H15="Paid",0,E15) | L15: =IF(J15=0,"Current",IF(J15<=30,"1-30 Days",IF(J15<=60,"31-60 Days",IF(J15<=90,"61-90 Days","90+ Days")))) | M15: =IF(Raw_Data!K15="Yes",Raw_Data!F15*Raw_Data!L15,0) | N15: =IF(H15<>"Paid","Outstanding",IF(J15=0,"On Time","Late"))
... A1003: =Raw_Data!A1003 | B1003: =Raw_Data!B1003 | C1003: =Raw_Data!C1003 | D1003: =Raw_Data!D1003 | E1003: =Raw_Data!F1003 | F1003: =Raw_Data!H1003 | G1003: =Raw_Data!I1003 | H1003: =Raw_Data!J1003 | I1003: =IF(G1003="",0,G1003-B1003) | J1003: =IF(H1003="Paid",MAX(0,G1003-F1003),MAX(0,DATE(2026,12,31)-F1003)) | K1003: =IF(H1003="Paid",0,E1003) | L1003: =IF(J1003=0,"Current",IF(J1003<=30,"1-30 Days",IF(J1003<=60,"31-60 Days",IF(J1003<=90,"61-90 Days","90+ Days")))) | M1003: =IF(Raw_Data!K1003="Yes",Raw_Data!F1003*Raw_Data!L1003,0) | N1003: =IF(H1003<>"Paid","Outstanding",IF(J1003=0,"On Time","Late"))

Sheet Aging_Analysis
A1: AP Aging Analysis
A3: Aging_Bucket | B3: Invoice_Count | C3: Outstanding_Amount | D3: % of Outstanding | E3: Management Meaning
A4: Current | B4: =COUNTIF(Calculated_Fields!L4:L1003,A4) | C4: =SUMIF(Calculated_Fields!L4:L1003,A4,Calculated_Fields!K4:K1003) | D4: =IFERROR(C4/SUM($C$4:$C$8),0) | E4: Not overdue
A5: 1-30 Days | B5: =COUNTIF(Calculated_Fields!L4:L1003,A5) | C5: =SUMIF(Calculated_Fields!L4:L1003,A5,Calculated_Fields!K4:K1003) | D5: =IFERROR(C5/SUM($C$4:$C$8),0) | E5: Early overdue
A6: 31-60 Days | B6: =COUNTIF(Calculated_Fields!L4:L1003,A6) | C6: =SUMIF(Calculated_Fields!L4:L1003,A6,Calculated_Fields!K4:K1003) | D6: =IFERROR(C6/SUM($C$4:$C$8),0) | E6: Moderate overdue
A7: 61-90 Days | B7: =COUNTIF(Calculated_Fields!L4:L1003,A7) | C7: =SUMIF(Calculated_Fields!L4:L1003,A7,Calculated_Fields!K4:K1003) | D7: =IFERROR(C7/SUM($C$4:$C$8),0) | E7: Significant overdue
A8: 90+ Days | B8: =COUNTIF(Calculated_Fields!L4:L1003,A8) | C8: =SUMIF(Calculated_Fields!L4:L1003,A8,Calculated_Fields!K4:K1003) | D8: =IFERROR(C8/SUM($C$4:$C$8),0) | E8: High-priority overdue
A10: Total Outstanding | C10: =SUM(C4:C8)

Sheet Vendor_Analysis
A1: Vendor-Level AP Analysis
A3: Vendor | B3: Invoice_Count | C3: Total_Invoice_Value | D3: Outstanding_AP | E3: Overdue_AP | F3: Overdue_Invoices | G3: Average_Days_Past_Due | H3: Discount_Opportunity | I3: % of Outstanding | J3: Priority
A4: Microsoft | B4: =COUNTIF(Calculated_Fields!C4:C1003,A4) | C4: =SUMIF(Calculated_Fields!C4:C1003,A4,Calculated_Fields!E4:E1003) | D4: =SUMIF(Calculated_Fields!C4:C1003,A4,Calculated_Fields!K4:K1003) | E4: =SUMIFS(Calculated_Fields!K4:K1003,Calculated_Fields!C4:C1003,A4,Calculated_Fields!J4:J1003,">0") | F4: =COUNTIFS(Calculated_Fields!C4:C1003,A4,Calculated_Fields!J4:J1003,">0",Calculated_Fields!K4:K1003,">0") | G4: =IFERROR(AVERAGEIFS(Calculated_Fields!J4:J1003,Calculated_Fields!C4:C1003,A4,Calculated_Fields!K4:K1003,">0"),0) | H4: =SUMIF(Calculated_Fields!C4:C1003,A4,Calculated_Fields!M4:M1003) | I4: =IFERROR(D4/SUM($D$4:$D$18),0) | J4: =IF(E4>=PERCENTILE($E$4:$E$18,0.75),"High",IF(E4>=PERCENTILE($E$4:$E$18,0.5),"Medium","Low"))
A5: Amazon Web Services | B5: =COUNTIF(Calculated_Fields!C4:C1003,A5) | C5: =SUMIF(Calculated_Fields!C4:C1003,A5,Calculated_Fields!E4:E1003) | D5: =SUMIF(Calculated_Fields!C4:C1003,A5,Calculated_Fields!K4:K1003) | E5: =SUMIFS(Calculated_Fields!K4:K1003,Calculated_Fields!C4:C1003,A5,Calculated_Fields!J4:J1003,">0") | F5: =COUNTIFS(Calculated_Fields!C4:C1003,A5,Calculated_Fields!J4:J1003,">0",Calculated_Fields!K4:K1003,">0") | G5: =IFERROR(AVERAGEIFS(Calculated_Fields!J4:J1003,Calculated_Fields!C4:C1003,A5,Calculated_Fields!K4:K1003,">0"),0) | H5: =SUMIF(Calculated_Fields!C4:C1003,A5,Calculated_Fields!M4:M1003) | I5: =IFERROR(D5/SUM($D$4:$D$18),0) | J5: =IF(E5>=PERCENTILE($E$4:$E$18,0.75),"High",IF(E5>=PERCENTILE($E$4:$E$18,0.5),"Medium","Low"))
A6: Deloitte | B6: =COUNTIF(Calculated_Fields!C4:C1003,A6) | C6: =SUMIF(Calculated_Fields!C4:C1003,A6,Calculated_Fields!E4:E1003) | D6: =SUMIF(Calculated_Fields!C4:C1003,A6,Calculated_Fields!K4:K1003) | E6: =SUMIFS(Calculated_Fields!K4:K1003,Calculated_Fields!C4:C1003,A6,Calculated_Fields!J4:J1003,">0") | F6: =COUNTIFS(Calculated_Fields!C4:C1003,A6,Calculated_Fields!J4:J1003,">0",Calculated_Fields!K4:K1003,">0") | G6: =IFERROR(AVERAGEIFS(Calculated_Fields!J4:J1003,Calculated_Fields!C4:C1003,A6,Calculated_Fields!K4:K1003,">0"),0) | H6: =SUMIF(Calculated_Fields!C4:C1003,A6,Calculated_Fields!M4:M1003) | I6: =IFERROR(D6/SUM($D$4:$D$18),0) | J6: =IF(E6>=PERCENTILE($E$4:$E$18,0.75),"High",IF(E6>=PERCENTILE($E$4:$E$18,0.5),"Medium","Low"))
A7: TCS | B7: =COUNTIF(Calculated_Fields!C4:C1003,A7) | C7: =SUMIF(Calculated_Fields!C4:C1003,A7,Calculated_Fields!E4:E1003) | D7: =SUMIF(Calculated_Fields!C4:C1003,A7,Calculated_Fields!K4:K1003) | E7: =SUMIFS(Calculated_Fields!K4:K1003,Calculated_Fields!C4:C1003,A7,Calculated_Fields!J4:J1003,">0") | F7: =COUNTIFS(Calculated_Fields!C4:C1003,A7,Calculated_Fields!J4:J1003,">0",Calculated_Fields!K4:K1003,">0") | G7: =IFERROR(AVERAGEIFS(Calculated_Fields!J4:J1003,Calculated_Fields!C4:C1003,A7,Calculated_Fields!K4:K1003,">0"),0) | H7: =SUMIF(Calculated_Fields!C4:C1003,A7,Calculated_Fields!M4:M1003) | I7: =IFERROR(D7/SUM($D$4:$D$18),0) | J7: =IF(E7>=PERCENTILE($E$4:$E$18,0.75),"High",IF(E7>=PERCENTILE($E$4:$E$18,0.5),"Medium","Low"))
A8: Infosys | B8: =COUNTIF(Calculated_Fields!C4:C1003,A8) | C8: =SUMIF(Calculated_Fields!C4:C1003,A8,Calculated_Fields!E4:E1003) | D8: =SUMIF(Calculated_Fields!C4:C1003,A8,Calculated_Fields!K4:K1003) | E8: =SUMIFS(Calculated_Fields!K4:K1003,Calculated_Fields!C4:C1003,A8,Calculated_Fields!J4:J1003,">0") | F8: =COUNTIFS(Calculated_Fields!C4:C1003,A8,Calculated_Fields!J4:J1003,">0",Calculated_Fields!K4:K1003,">0") | G8: =IFERROR(AVERAGEIFS(Calculated_Fields!J4:J1003,Calculated_Fields!C4:C1003,A8,Calculated_Fields!K4:K1003,">0"),0) | H8: =SUMIF(Calculated_Fields!C4:C1003,A8,Calculated_Fields!M4:M1003) | I8: =IFERROR(D8/SUM($D$4:$D$18),0) | J8: =IF(E8>=PERCENTILE($E$4:$E$18,0.75),"High",IF(E8>=PERCENTILE($E$4:$E$18,0.5),"Medium","Low"))
A9: Oracle | B9: =COUNTIF(Calculated_Fields!C4:C1003,A9) | C9: =SUMIF(Calculated_Fields!C4:C1003,A9,Calculated_Fields!E4:E1003) | D9: =SUMIF(Calculated_Fields!C4:C1003,A9,Calculated_Fields!K4:K1003) | E9: =SUMIFS(Calculated_Fields!K4:K1003,Calculated_Fields!C4:C1003,A9,Calculated_Fields!J4:J1003,">0") | F9: =COUNTIFS(Calculated_Fields!C4:C1003,A9,Calculated_Fields!J4:J1003,">0",Calculated_Fields!K4:K1003,">0") | G9: =IFERROR(AVERAGEIFS(Calculated_Fields!J4:J1003,Calculated_Fields!C4:C1003,A9,Calculated_Fields!K4:K1003,">0"),0) | H9: =SUMIF(Calculated_Fields!C4:C1003,A9,Calculated_Fields!M4:M1003) | I9: =IFERROR(D9/SUM($D$4:$D$18),0) | J9: =IF(E9>=PERCENTILE($E$4:$E$18,0.75),"High",IF(E9>=PERCENTILE($E$4:$E$18,0.5),"Medium","Low"))
A10: Adobe | B10: =COUNTIF(Calculated_Fields!C4:C1003,A10) | C10: =SUMIF(Calculated_Fields!C4:C1003,A10,Calculated_Fields!E4:E1003) | D10: =SUMIF(Calculated_Fields!C4:C1003,A10,Calculated_Fields!K4:K1003) | E10: =SUMIFS(Calculated_Fields!K4:K1003,Calculated_Fields!C4:C1003,A10,Calculated_Fields!J4:J1003,">0") | F10: =COUNTIFS(Calculated_Fields!C4:C1003,A10,Calculated_Fields!J4:J1003,">0",Calculated_Fields!K4:K1003,">0") | G10: =IFERROR(AVERAGEIFS(Calculated_Fields!J4:J1003,Calculated_Fields!C4:C1003,A10,Calculated_Fields!K4:K1003,">0"),0) | H10: =SUMIF(Calculated_Fields!C4:C1003,A10,Calculated_Fields!M4:M1003) | I10: =IFERROR(D10/SUM($D$4:$D$18),0) | J10: =IF(E10>=PERCENTILE($E$4:$E$18,0.75),"High",IF(E10>=PERCENTILE($E$4:$E$18,0.5),"Medium","Low"))
A11: IBM | B11: =COUNTIF(Calculated_Fields!C4:C1003,A11) | C11: =SUMIF(Calculated_Fields!C4:C1003,A11,Calculated_Fields!E4:E1003) | D11: =SUMIF(Calculated_Fields!C4:C1003,A11,Calculated_Fields!K4:K1003) | E11: =SUMIFS(Calculated_Fields!K4:K1003,Calculated_Fields!C4:C1003,A11,Calculated_Fields!J4:J1003,">0") | F11: =COUNTIFS(Calculated_Fields!C4:C1003,A11,Calculated_Fields!J4:J1003,">0",Calculated_Fields!K4:K1003,">0") | G11: =IFERROR(AVERAGEIFS(Calculated_Fields!J4:J1003,Calculated_Fields!C4:C1003,A11,Calculated_Fields!K4:K1003,">0"),0) | H11: =SUMIF(Calculated_Fields!C4:C1003,A11,Calculated_Fields!M4:M1003) | I11: =IFERROR(D11/SUM($D$4:$D$18),0) | J11: =IF(E11>=PERCENTILE($E$4:$E$18,0.75),"High",IF(E11>=PERCENTILE($E$4:$E$18,0.5),"Medium","Low"))
A12: Google Cloud | B12: =COUNTIF(Calculated_Fields!C4:C1003,A12) | C12: =SUMIF(Calculated_Fields!C4:C1003,A12,Calculated_Fields!E4:E1003) | D12: =SUMIF(Calculated_Fields!C4:C1003,A12,Calculated_Fields!K4:K1003) | E12: =SUMIFS(Calculated_Fields!K4:K1003,Calculated_Fields!C4:C1003,A12,Calculated_Fields!J4:J1003,">0") | F12: =COUNTIFS(Calculated_Fields!C4:C1003,A12,Calculated_Fields!J4:J1003,">0",Calculated_Fields!K4:K1003,">0") | G12: =IFERROR(AVERAGEIFS(Calculated_Fields!J4:J1003,Calculated_Fields!C4:C1003,A12,Calculated_Fields!K4:K1003,">0"),0) | H12: =SUMIF(Calculated_Fields!C4:C1003,A12,Calculated_Fields!M4:M1003) | I12: =IFERROR(D12/SUM($D$4:$D$18),0) | J12: =IF(E12>=PERCENTILE($E$4:$E$18,0.75),"High",IF(E12>=PERCENTILE($E$4:$E$18,0.5),"Medium","Low"))
A13: Accenture | B13: =COUNTIF(Calculated_Fields!C4:C1003,A13) | C13: =SUMIF(Calculated_Fields!C4:C1003,A13,Calculated_Fields!E4:E1003) | D13: =SUMIF(Calculated_Fields!C4:C1003,A13,Calculated_Fields!K4:K1003) | E13: =SUMIFS(Calculated_Fields!K4:K1003,Calculated_Fields!C4:C1003,A13,Calculated_Fields!J4:J1003,">0") | F13: =COUNTIFS(Calculated_Fields!C4:C1003,A13,Calculated_Fields!J4:J1003,">0",Calculated_Fields!K4:K1003,">0") | G13: =IFERROR(AVERAGEIFS(Calculated_Fields!J4:J1003,Calculated_Fields!C4:C1003,A13,Calculated_Fields!K4:K1003,">0"),0) | H13: =SUMIF(Calculated_Fields!C4:C1003,A13,Calculated_Fields!M4:M1003) | I13: =IFERROR(D13/SUM($D$4:$D$18),0) | J13: =IF(E13>=PERCENTILE($E$4:$E$18,0.75),"High",IF(E13>=PERCENTILE($E$4:$E$18,0.5),"Medium","Low"))
A14: SAP | B14: =COUNTIF(Calculated_Fields!C4:C1003,A14) | C14: =SUMIF(Calculated_Fields!C4:C1003,A14,Calculated_Fields!E4:E1003) | D14: =SUMIF(Calculated_Fields!C4:C1003,A14,Calculated_Fields!K4:K1003) | E14: =SUMIFS(Calculated_Fields!K4:K1003,Calculated_Fields!C4:C1003,A14,Calculated_Fields!J4:J1003,">0") | F14: =COUNTIFS(Calculated_Fields!C4:C1003,A14,Calculated_Fields!J4:J1003,">0",Calculated_Fields!K4:K1003,">0") | G14: =IFERROR(AVERAGEIFS(Calculated_Fields!J4:J1003,Calculated_Fields!C4:C1003,A14,Calculated_Fields!K4:K1003,">0"),0) | H14: =SUMIF(Calculated_Fields!C4:C1003,A14,Calculated_Fields!M4:M1003) | I14: =IFERROR(D14/SUM($D$4:$D$18),0) | J14: =IF(E14>=PERCENTILE($E$4:$E$18,0.75),"High",IF(E14>=PERCENTILE($E$4:$E$18,0.5),"Medium","Low"))
A15: Wipro | B15: =COUNTIF(Calculated_Fields!C4:C1003,A15) | C15: =SUMIF(Calculated_Fields!C4:C1003,A15,Calculated_Fields!E4:E1003) | D15: =SUMIF(Calculated_Fields!C4:C1003,A15,Calculated_Fields!K4:K1003) | E15: =SUMIFS(Calculated_Fields!K4:K1003,Calculated_Fields!C4:C1003,A15,Calculated_Fields!J4:J1003,">0") | F15: =COUNTIFS(Calculated_Fields!C4:C1003,A15,Calculated_Fields!J4:J1003,">0",Calculated_Fields!K4:K1003,">0") | G15: =IFERROR(AVERAGEIFS(Calculated_Fields!J4:J1003,Calculated_Fields!C4:C1003,A15,Calculated_Fields!K4:K1003,">0"),0) | H15: =SUMIF(Calculated_Fields!C4:C1003,A15,Calculated_Fields!M4:M1003) | I15: =IFERROR(D15/SUM($D$4:$D$18),0) | J15: =IF(E15>=PERCENTILE($E$4:$E$18,0.75),"High",IF(E15>=PERCENTILE($E$4:$E$18,0.5),"Medium","Low"))
A16: Cognizant | B16: =COUNTIF(Calculated_Fields!C4:C1003,A16) | C16: =SUMIF(Calculated_Fields!C4:C1003,A16,Calculated_Fields!E4:E1003) | D16: =SUMIF(Calculated_Fields!C4:C1003,A16,Calculated_Fields!K4:K1003) | E16: =SUMIFS(Calculated_Fields!K4:K1003,Calculated_Fields!C4:C1003,A16,Calculated_Fields!J4:J1003,">0") | F16: =COUNTIFS(Calculated_Fields!C4:C1003,A16,Calculated_Fields!J4:J1003,">0",Calculated_Fields!K4:K1003,">0") | G16: =IFERROR(AVERAGEIFS(Calculated_Fields!J4:J1003,Calculated_Fields!C4:C1003,A16,Calculated_Fields!K4:K1003,">0"),0) | H16: =SUMIF(Calculated_Fields!C4:C1003,A16,Calculated_Fields!M4:M1003) | I16: =IFERROR(D16/SUM($D$4:$D$18),0) | J16: =IF(E16>=PERCENTILE($E$4:$E$18,0.75),"High",IF(E16>=PERCENTILE($E$4:$E$18,0.5),"Medium","Low"))
A17: HCLTech | B17: =COUNTIF(Calculated_Fields!C4:C1003,A17) | C17: =SUMIF(Calculated_Fields!C4:C1003,A17,Calculated_Fields!E4:E1003) | D17: =SUMIF(Calculated_Fields!C4:C1003,A17,Calculated_Fields!K4:K1003) | E17: =SUMIFS(Calculated_Fields!K4:K1003,Calculated_Fields!C4:C1003,A17,Calculated_Fields!J4:J1003,">0") | F17: =COUNTIFS(Calculated_Fields!C4:C1003,A17,Calculated_Fields!J4:J1003,">0",Calculated_Fields!K4:K1003,">0") | G17: =IFERROR(AVERAGEIFS(Calculated_Fields!J4:J1003,Calculated_Fields!C4:C1003,A17,Calculated_Fields!K4:K1003,">0"),0) | H17: =SUMIF(Calculated_Fields!C4:C1003,A17,Calculated_Fields!M4:M1003) | I17: =IFERROR(D17/SUM($D$4:$D$18),0) | J17: =IF(E17>=PERCENTILE($E$4:$E$18,0.75),"High",IF(E17>=PERCENTILE($E$4:$E$18,0.5),"Medium","Low"))
A18: Zoho | B18: =COUNTIF(Calculated_Fields!C4:C1003,A18) | C18: =SUMIF(Calculated_Fields!C4:C1003,A18,Calculated_Fields!E4:E1003) | D18: =SUMIF(Calculated_Fields!C4:C1003,A18,Calculated_Fields!K4:K1003) | E18: =SUMIFS(Calculated_Fields!K4:K1003,Calculated_Fields!C4:C1003,A18,Calculated_Fields!J4:J1003,">0") | F18: =COUNTIFS(Calculated_Fields!C4:C1003,A18,Calculated_Fields!J4:J1003,">0",Calculated_Fields!K4:K1003,">0") | G18: =IFERROR(AVERAGEIFS(Calculated_Fields!J4:J1003,Calculated_Fields!C4:C1003,A18,Calculated_Fields!K4:K1003,">0"),0) | H18: =SUMIF(Calculated_Fields!C4:C1003,A18,Calculated_Fields!M4:M1003) | I18: =IFERROR(D18/SUM($D$4:$D$18),0) | J18: =IF(E18>=PERCENTILE($E$4:$E$18,0.75),"High",IF(E18>=PERCENTILE($E$4:$E$18,0.5),"Medium","Low"))

Sheet Department_Analysis
A1: Department AP Analysis
A3: Department | B3: Invoice_Count | C3: Total_Invoice_Value | D3: Outstanding_AP | E3: Overdue_AP | F3: Overdue_% | G3: Avg_Payment_Days | H3: Avg_Days_Past_Due | I3: Discount_Opportunity
A4: IT | B4: =COUNTIF(Calculated_Fields!D4:D1003,A4) | C4: =SUMIF(Calculated_Fields!D4:D1003,A4,Calculated_Fields!E4:E1003) | D4: =SUMIF(Calculated_Fields!D4:D1003,A4,Calculated_Fields!K4:K1003) | E4: =SUMIFS(Calculated_Fields!K4:K1003,Calculated_Fields!D4:D1003,A4,Calculated_Fields!J4:J1003,">0") | F4: =IFERROR(E4/D4,0) | G4: =IFERROR(AVERAGEIFS(Calculated_Fields!I4:I1003,Calculated_Fields!D4:D1003,A4,Calculated_Fields!I4:I1003,">0"),0) | H4: =IFERROR(AVERAGEIFS(Calculated_Fields!J4:J1003,Calculated_Fields!D4:D1003,A4,Calculated_Fields!J4:J1003,">0"),0) | I4: =SUMIFS(Calculated_Fields!M4:M1003,Calculated_Fields!D4:D1003,A4)
A5: Finance | B5: =COUNTIF(Calculated_Fields!D4:D1003,A5) | C5: =SUMIF(Calculated_Fields!D4:D1003,A5,Calculated_Fields!E4:E1003) | D5: =SUMIF(Calculated_Fields!D4:D1003,A5,Calculated_Fields!K4:K1003) | E5: =SUMIFS(Calculated_Fields!K4:K1003,Calculated_Fields!D4:D1003,A5,Calculated_Fields!J4:J1003,">0") | F5: =IFERROR(E5/D5,0) | G5: =IFERROR(AVERAGEIFS(Calculated_Fields!I4:I1003,Calculated_Fields!D4:D1003,A5,Calculated_Fields!I4:I1003,">0"),0) | H5: =IFERROR(AVERAGEIFS(Calculated_Fields!J4:J1003,Calculated_Fields!D4:D1003,A5,Calculated_Fields!J4:J1003,">0"),0) | I5: =SUMIFS(Calculated_Fields!M4:M1003,Calculated_Fields!D4:D1003,A5)
A6: HR | B6: =COUNTIF(Calculated_Fields!D4:D1003,A6) | C6: =SUMIF(Calculated_Fields!D4:D1003,A6,Calculated_Fields!E4:E1003) | D6: =SUMIF(Calculated_Fields!D4:D1003,A6,Calculated_Fields!K4:K1003) | E6: =SUMIFS(Calculated_Fields!K4:K1003,Calculated_Fields!D4:D1003,A6,Calculated_Fields!J4:J1003,">0") | F6: =IFERROR(E6/D6,0) | G6: =IFERROR(AVERAGEIFS(Calculated_Fields!I4:I1003,Calculated_Fields!D4:D1003,A6,Calculated_Fields!I4:I1003,">0"),0) | H6: =IFERROR(AVERAGEIFS(Calculated_Fields!J4:J1003,Calculated_Fields!D4:D1003,A6,Calculated_Fields!J4:J1003,">0"),0) | I6: =SUMIFS(Calculated_Fields!M4:M1003,Calculated_Fields!D4:D1003,A6)
A7: Operations | B7: =COUNTIF(Calculated_Fields!D4:D1003,A7) | C7: =SUMIF(Calculated_Fields!D4:D1003,A7,Calculated_Fields!E4:E1003) | D7: =SUMIF(Calculated_Fields!D4:D1003,A7,Calculated_Fields!K4:K1003) | E7: =SUMIFS(Calculated_Fields!K4:K1003,Calculated_Fields!D4:D1003,A7,Calculated_Fields!J4:J1003,">0") | F7: =IFERROR(E7/D7,0) | G7: =IFERROR(AVERAGEIFS(Calculated_Fields!I4:I1003,Calculated_Fields!D4:D1003,A7,Calculated_Fields!I4:I1003,">0"),0) | H7: =IFERROR(AVERAGEIFS(Calculated_Fields!J4:J1003,Calculated_Fields!D4:D1003,A7,Calculated_Fields!J4:J1003,">0"),0) | I7: =SUMIFS(Calculated_Fields!M4:M1003,Calculated_Fields!D4:D1003,A7)
A8: Marketing | B8: =COUNTIF(Calculated_Fields!D4:D1003,A8) | C8: =SUMIF(Calculated_Fields!D4:D1003,A8,Calculated_Fields!E4:E1003) | D8: =SUMIF(Calculated_Fields!D4:D1003,A8,Calculated_Fields!K4:K1003) | E8: =SUMIFS(Calculated_Fields!K4:K1003,Calculated_Fields!D4:D1003,A8,Calculated_Fields!J4:J1003,">0") | F8: =IFERROR(E8/D8,0) | G8: =IFERROR(AVERAGEIFS(Calculated_Fields!I4:I1003,Calculated_Fields!D4:D1003,A8,Calculated_Fields!I4:I1003,">0"),0) | H8: =IFERROR(AVERAGEIFS(Calculated_Fields!J4:J1003,Calculated_Fields!D4:D1003,A8,Calculated_Fields!J4:J1003,">0"),0) | I8: =SUMIFS(Calculated_Fields!M4:M1003,Calculated_Fields!D4:D1003,A8)
A9: Sales | B9: =COUNTIF(Calculated_Fields!D4:D1003,A9) | C9: =SUMIF(Calculated_Fields!D4:D1003,A9,Calculated_Fields!E4:E1003) | D9: =SUMIF(Calculated_Fields!D4:D1003,A9,Calculated_Fields!K4:K1003) | E9: =SUMIFS(Calculated_Fields!K4:K1003,Calculated_Fields!D4:D1003,A9,Calculated_Fields!J4:J1003,">0") | F9: =IFERROR(E9/D9,0) | G9: =IFERROR(AVERAGEIFS(Calculated_Fields!I4:I1003,Calculated_Fields!D4:D1003,A9,Calculated_Fields!I4:I1003,">0"),0) | H9: =IFERROR(AVERAGEIFS(Calculated_Fields!J4:J1003,Calculated_Fields!D4:D1003,A9,Calculated_Fields!J4:J1003,">0"),0) | I9: =SUMIFS(Calculated_Fields!M4:M1003,Calculated_Fields!D4:D1003,A9)

Sheet Working_Capital
A1: Working Capital Analysis
A3: Metric | B3: Value | C3: Formula / Method | D3: Interpretation
A4: Total Invoice Value | B4: =SUM(Calculated_Fields!E4:E1003) | C4: Sum of all invoice amounts | D4: Total AP activity represented by dataset.
A5: Outstanding AP | B5: =SUM(Calculated_Fields!K4:K1003) | C5: Sum of unpaid invoice balances | D5: Cash still payable to suppliers.
A6: Overdue AP | B6: =SUMIFS(Calculated_Fields!K4:K1003,Calculated_Fields!J4:J1003,">0") | C6: Outstanding balance with days past due > 0 | D6: Potential payment bottleneck / supplier-management issue.
A7: Overdue % | B7: =IFERROR(B6/B5,0) | C7: Overdue AP / Outstanding AP | D7: Share of outstanding AP that is overdue.
A8: Average Payment Days | B8: =AVERAGEIFS(Calculated_Fields!I4:I1003,Calculated_Fields!I4:I1003,">0") | C8: Average invoice-to-payment days for paid invoices | D8: Describes payment timing.
A9: Discount Opportunity | B9: =SUM(Calculated_Fields!M4:M1003) | C9: Invoice value × discount % where available | D9: Potential value from early-payment discounts.
A10: Illustrative Annual Purchases | B10: =B5*12 | C10: Assumption: monthly AP run-rate × 12 | D10: Portfolio assumption only; replace with actual annual purchases/COGS.
A11: Illustrative DPO | B11: =IFERROR((B5/B10)*365,0) | C11: Outstanding AP / annualized purchases × 365 | D11: Simplified DPO proxy; not a substitute for company-specific DPO methodology.

Sheet Dashboard
A1: AP & Working Capital Management Dashboard
A3: Total AP | E3: Outstanding AP | I3: Overdue AP
A4: =Working_Capital!B4 | E4: =Working_Capital!B5 | I4: =Working_Capital!B6
A7: Overdue % | E7: Avg Payment Days | I7: Discount Opportunity
A8: =Working_Capital!B7 | E8: =Working_Capital!B8 | I8: =Working_Capital!B9
A12: Aging Bucket | B12: Current | C12: 1-30 Days | D12: 31-60 Days | E12: 61-90 Days | F12: 90+ Days
A13: Outstanding AP | B13: =Aging_Analysis!C4 | C13: =Aging_Analysis!C5 | D13: =Aging_Analysis!C6 | E13: =Aging_Analysis!C7 | F13: =Aging_Analysis!C8
A25: Vendor | B25: Outstanding AP
A26: =Vendor_Analysis!A4 | B26: =Vendor_Analysis!D4
A27: =Vendor_Analysis!A5 | B27: =Vendor_Analysis!D5
A28: =Vendor_Analysis!A6 | B28: =Vendor_Analysis!D6
A29: =Vendor_Analysis!A7 | B29: =Vendor_Analysis!D7
A30: =Vendor_Analysis!A8 | B30: =Vendor_Analysis!D8
A31: =Vendor_Analysis!A9 | B31: =Vendor_Analysis!D9
A32: =Vendor_Analysis!A10 | B32: =Vendor_Analysis!D10
A33: =Vendor_Analysis!A11 | B33: =Vendor_Analysis!D11
A34: =Vendor_Analysis!A12 | B34: =Vendor_Analysis!D12
A35: =Vendor_Analysis!A13 | B35: =Vendor_Analysis!D13
A36: =Vendor_Analysis!A14 | B36: =Vendor_Analysis!D14
A37: =Vendor_Analysis!A15 | B37: =Vendor_Analysis!D15
... A40: =Vendor_Analysis!A18 | B40: =Vendor_Analysis!D18

Sheet Insights
A1: Analyst Insights Framework
A3: 1. AP exposure | B3: Identify the total outstanding balance and quantify how much is overdue.
A4: 2. Aging | B4: Focus management attention on 61–90 and 90+ day balances rather than treating all overdue invoices equally.
A5: 3. Vendor concentration | B5: Review whether a small number of vendors account for a large share of outstanding AP.
A6: 4. Process bottlenecks | B6: Use department-level overdue % and days past due to investigate approval, GRN or invoice-processing delays.
A7: 5. Cash management | B7: Later payment within agreed terms can preserve cash, while missed early-payment discounts can represent a measurable opportunity cost.
A8: 6. Data limitation | B8: The dataset is synthetic. The findings demonstrate the analytical method, not actual company performance.

Sheet Sources
A1: Sources & Methodology
A3: Dataset | B3: Synthetic portfolio dataset | C3: Generated for learning; not company data.
A4: Aging as-of date | B4: 31-Dec-2026 | C4: Used for unpaid invoice aging.
A5: Payment days | B5: Payment Date − Invoice Date | C5: Paid invoices only.
A6: Days past due | B6: MAX(0, Payment Date − Due Date) for paid; As-of Date − Due Date for unpaid | C6: Simplified portfolio methodology.
A7: DPO | B7: Outstanding AP / annualized purchases × 365 | C7: Illustrative proxy. Replace with actual average AP and annual COGS/purchases in a real company model.
A8: Discount opportunity | B8: Invoice amount × discount % when discount is available | C8: Potential discount value, not realized savings.
A12: Recommended real-data sources
A13: Company ERP / AP subledger | B13: Primary source for invoice, vendor, payment and due-date data.
A14: Purchase Orders / GRNs | B14: Validate three-way match and receiving bottlenecks.
A15: General Ledger | B15: Reconcile AP subledger totals to the financial statements.

Sheet Reverse_Engineering
A1: Reverse Engineering Guide
A3: Step | B3: Sheet | C3: What to inspect | D3: Why it matters
A4: 1 | B4: Raw_Data | C4: Understand invoice-level fields, dates, statuses and amounts. | D4: Every analysis begins with transaction-level data.
A5: 2 | B5: Calculated_Fields | C5: Trace Payment Days, Days Past Due, Outstanding Amount and Aging Bucket formulas. | D5: This converts raw transactions into analytical variables.
A6: 3 | B6: Aging_Analysis | C6: Follow COUNTIF/SUMIF aggregation by aging bucket. | D6: Shows where overdue cash obligations are concentrated.
A7: 4 | B7: Vendor_Analysis | C7: Trace vendor-level SUMIF/SUMIFS and priority logic. | D7: Identifies supplier concentration and payment-risk areas.
A8: 5 | B8: Department_Analysis | C8: Compare overdue %, payment days and discount opportunity by department. | D8: Helps locate process bottlenecks.
A9: 6 | B9: Working_Capital | C9: Understand AP, overdue AP, payment timing and the simplified DPO proxy. | D9: Connects operational AP activity to working-capital management.
A10: 7 | B10: Dashboard | C10: Trace each KPI and chart back to the underlying sheet. | D10: Shows how analysts communicate results to management.
A11: 8 | B11: Insights | C11: Turn numerical patterns into questions and actions. | D11: Financial analysts do not stop at reporting numbers.
